entrada timer e controle/mux.v
module mux(input wire sel,inA,inB,output wire pgt_1Hz);
	assign pgt_1Hz= (!sel&inA)|(sel&inB);// implementação de um mux com portas lógicas
endmodule

entrada timer e controle/mux/mux_tb.v
`timescale 1ns/1ns
module mux_tb();
reg sel_tb=0,inA_tb,inB_tb;
wire pgt_1Hz_tb;
integer i;
mux DUT(.sel(sel_tb),.inA(inA_tb),.inB(inB_tb),.pgt_1Hz(pgt_1Hz_tb));
initial begin
	$dumpfile("mux_tb.vcd");
	$dumpvars(0,mux_tb);
	i=0;
	repeat(2)begin
		for(i=0;i<4;i=i+1)begin
			{inA_tb,inB_tb}=i;
			#10;
		end
		sel_tb=sel_tb^1;//como inicialmente o sel_tb é 0. 0 xor(^) 1 = 1. 
	end
end
endmodule

entrada timer e controle/mux/mux_tb.vcd
$date
	Sun Apr 25 13:01:46 2021
$end
$version
	Icarus Verilog
$end
$timescale
	1ns
$end
$scope module mux_tb $end
$var wire 1 ! pgt_1Hz_tb $end
$var reg 1 " inA_tb $end
$var reg 1 # inB_tb $end
$var reg 1 $ sel_tb $end
$var integer 32 % i [31:0] $end
$scope module DUT $end
$var wire 1 " inA $end
$var wire 1 # inB $end
$var wire 1 ! pgt_1Hz $end
$var wire 1 $ sel $end
$upscope $end
$upscope $end
$enddefinitions $end
#0
$dumpvars
b0 %
0$
0#
0"
0!
$end
#10
1#
b1 %
#20
1!
1"
0#
b10 %
#30
1#
b11 %
#40
0!
0"
0#
1$
b0 %
#50
1!
1#
b1 %
#60
0!
1"
0#
b10 %
#70
1!
1#
b11 %
#80
0$
b100 %
