microondas/bcd_7segmentos.v
module bcd_7segmentos(input wire [3:0]mins,sec_tens,sec_ones, output reg [6:0]min_segs,sec_tens_segs,sec_ones_segs);
always@* begin
	case(mins)			  
		4'b0000: min_segs = 7'b0000001;
        4'b0001: min_segs = 7'b1001111;
        4'b0010: min_segs = 7'b0010010;
        4'b0011: min_segs = 7'b0000110;
        4'b0100: min_segs = 7'b1001100;
        4'b0101: min_segs = 7'b0100100;
        4'b0110: min_segs = 7'b0100000;
        4'b0111: min_segs = 7'b0001111;
        4'b1000: min_segs = 7'b0000000;
        4'b1001: min_segs = 7'b0001100;
		default: min_segs = 7'b1111111;
	endcase
	case(sec_tens)			  
		4'b0000: sec_tens_segs = 7'b0000001;
        4'b0001: sec_tens_segs = 7'b1001111;
        4'b0010: sec_tens_segs = 7'b0010010;
        4'b0011: sec_tens_segs = 7'b0000110;
        4'b0100: sec_tens_segs = 7'b1001100;
        4'b0101: sec_tens_segs = 7'b0100100;
        4'b0110: sec_tens_segs = 7'b0100000;
        4'b0111: sec_tens_segs = 7'b0001111;
        4'b1000: sec_tens_segs = 7'b0000000;
        4'b1001: sec_tens_segs = 7'b0001100;
		default: sec_tens_segs = 7'b1111111;
	endcase
	case(sec_ones)			  
		4'b0000: sec_ones_segs = 7'b0000001;
        4'b0001: sec_ones_segs = 7'b1001111;
        4'b0010: sec_ones_segs = 7'b0010010;
        4'b0011: sec_ones_segs = 7'b0000110;
        4'b0100: sec_ones_segs = 7'b1001100;
        4'b0101: sec_ones_segs = 7'b0100100;
        4'b0110: sec_ones_segs = 7'b0100000;
        4'b0111: sec_ones_segs = 7'b0001111;
        4'b1000: sec_ones_segs = 7'b0000000;
        4'b1001: sec_ones_segs = 7'b0001100;
		default: sec_ones_segs = 7'b1111111;
	endcase
end
endmodule

timer min seg/contadormod10.v
module contadormod10(input wire [3:0] data, input wire loadneg,clearneg,clk,en,output reg [3:0] out,output reg tc,zero);
initial begin
	out<=0;
	zero<=1;
	tc<=0;
end
always @(posedge clk or negedge clearneg) begin
	if(!clearneg)begin
		out<=0; zero<=1; tc<=1;
	end
	else if(!loadneg)begin
		out<=data; zero<=(data==0)?1:0;
	end
	else begin
		if(en) begin
			out<=out-1;
			case(out)
				4'b0001:begin zero<=1; tc<=1; end// esta definido no 1 porque a alteração so ocorre no próximo pulso de clock
				4'b0000:begin out<=9;zero<=0; tc<=0; end// explicação análoga a da linha acima
				default:begin zero<=0; tc<=0; end
			endcase
		end
		else begin
			out<=out; tc<=0; 
		end
	end
end
endmodule

timer min seg/contadormod6.v
module contadormod6(input wire [3:0] data, input wire loadneg,clearneg,clk,en,output reg [3:0] out,output reg tc,zero);
initial begin
	out<=0;
	zero<=1;
	tc<=0;
end
always @(posedge clk or negedge clearneg) begin
	if(!clearneg)begin
		out<=0; zero<=1; tc<=1;
	end
	else if(!loadneg)begin
		out<=data; zero<=(data==0)?1:0;
	end
	else begin
		if(en) begin
			out<=out-1;
			case(out)
				4'b0001:begin zero<=1; tc<=1; end// esta definido no 1 porque a alteração so ocorre no proximo pulso de clock
				4'b0000:begin out<=5;zero<=0; tc<=0; end// explicação análoga a da linha acima
				default:begin zero<=0; tc<=0; end
			endcase
		end
		else begin
			out<=out; tc<=0; 
		end
	end
end
endmodule

microondas/timerminseg.v
module timerminseg(input wire [3:0] data, input wire loadn,clrn,clock,enable,output wire zero,output wire [3:0] sec_ones,sec_tens,mins);

wire tcSecOnes,tcSecTens,tcMins,zeroSecOnes,zeroSecTens,zeroMins;
wire tcSecTenstoMins;// feito por conta do minuto estar sendo decrementado na hora errada. agora só decrementa quando os segundos terminarem
assign tcSecTenstoMins=zeroSecOnes&zeroSecTens&tcSecOnes; 
contadormod10 U0 (.data(data),.loadneg(loadn),.clearneg(clrn),.clk(clock),.en(enable),.tc(tcSecOnes),.zero(zeroSecOnes),.out(sec_ones));
contadormod6 U1 (.data(sec_ones),.loadneg(loadn),.clearneg(clrn),.clk(clock),.en(tcSecOnes),.tc(tcSecTens),.zero(zeroSecTens),.out(sec_tens));
contadormod10 U2 (.data(sec_tens),.loadneg(loadn),.clearneg(clrn),.clk(clock),.en(tcSecTenstoMins),.tc(tcMins),.zero(zeroMins),.out(mins));
assign zero =  zeroSecOnes & zeroSecTens & zeroMins;

endmodule

microondas/mag_on.v
module mag_on(
  input wire STARTN, STOPN, CLEARN, DOOR, timer_done,
  output wire mag
);
  
  wire nq, SET, RESET;
  
  assign RESET = STARTN | !STOPN | !CLEARN | !DOOR | timer_done;
  assign SET = !STARTN & STOPN & CLEARN & DOOR & !timer_done;
  
  nor g1(mag, RESET, nq);
  nor g2(nq, SET, mag);
endmodule

entrada timer e controle/mux.v
module mux(input wire sel,inA,inB,output wire pgt_1Hz);
	assign pgt_1Hz= (!sel&inA)|(sel&inB);// implementação de um mux com portas lógicas
endmodule

microondas/delaydebouncing.v
module delaydebouncing(input wire clear, clk,output reg key);
reg [2:0] count;
initial begin
	count<=0;
	key<=0;
end
always @(posedge clk or posedge clear) begin
	if (clear) begin
		count<=0;
		key<=0;
	end
	case(count)
		3'b011:begin key<=1; count<=count+1; end// considerando o 011(2)==3(10) porque a mudança só acontece após o pulso de clock
		3'b110:begin key<=0; count<=count+1; end// mesma consideração aqui
		3'b111:count<=0;
		default:count<=count+1;
	endcase
end
endmodule

entrada timer e controle/codificadorKeypadBCD/priorityEncoder.v
module priorityEncoder(input wire [9:0] keypad,input wire enablen, output reg [3:0] out,output reg dataVal);
always@* begin
	if(!enablen)begin
	    case(keypad)
	    	10'b0000000001:begin out=4'b0000; dataVal=1'b0; end
	    	10'b0000000010:begin out=4'b0001; dataVal=1'b0; end
	    	10'b0000000100:begin out=4'b0010; dataVal=1'b0; end
	    	10'b0000001000:begin out=4'b0011; dataVal=1'b0; end
	    	10'b0000010000:begin out=4'b0100; dataVal=1'b0; end
	    	10'b0000100000:begin out=4'b0101; dataVal=1'b0; end
	    	10'b0001000000:begin out=4'b0110; dataVal=1'b0; end
	    	10'b0010000000:begin out=4'b0111; dataVal=1'b0; end
	    	10'b0100000000:begin out=4'b1000; dataVal=1'b0; end
	    	10'b1000000000:begin out=4'b1001; dataVal=1'b0; end
	    	default:begin out=4'bXXXX; dataVal=1'b1; end
	    endcase
	end
	else begin
		out=4'bXXXX; dataVal=1'b1;
	end
end
endmodule

entrada timer e controle/clockdiv100/clkdiv100.v
module clkdiv100(input wire clk, output reg clk100);
reg [5:0] count;
initial begin
	clk100<=0;
	count<=0;
end
always @(posedge clk) begin
	case(count) //verifico se o contador é 49. 49 porque é necessário um clock de 1Hz(ou seja, um período de 1s compostdo de clk100=1 quando tempo=0.5s e clk100=0 quando tempo=1s)
		6'b110001:begin count<=0; clk100<=clk100^1; end// clk100 == clk100 xor 1 (o comportamento é fazer o valor de clk100 ser '1' e depois '0'). O valor binário é 49(base10)
		default:count<=count+1;
	endcase
end
endmodule

microondas/timerAndControlInput.v
module timerAndControlInput(input wire [9:0] keypad,input wire enablen,clk,output wire loadn,pgt_1Hz,output wire [3:0] D);
wire inB,inA;//conectando a saída do clock/100 ao fio inB para colocar na entrada. para o inA, é a saída dos pulsos para colocar o dígito válido no timer
clkdiv100 U0 (.clk(clk),.clk100(inB));
priorityEncoder U1 (.keypad(keypad),.enablen(enablen),.out(D),.dataVal(loadn));
delaydebouncing U2 (.clk(clk),.clear(loadn),.key(inA));
mux U3 (.sel(enablen),.inA(inA),.inB(inB),.pgt_1Hz(pgt_1Hz));

endmodule

microondas/microwaveOven.v
module microwaveOven(input wire [9:0]keypad,input wire startn,stopn,clearn,door_closed,clock, output wire mag_on,output wire [6:0] sec_ones_segs,sec_tens_segs,min_segs);
reg count=0;// variável para auxiliar no processo de reativação do contador do microondas
wire [3:0] D_out,sec_ones_out,sec_tens_out,mins_out;
wire loadn_out,pgt_1Hz_out,zero_out,pgt_1Hz_out_canPulse;
reg canPulse=1;// estado inicial. tudo normal

assign pgt_1Hz_out_canPulse = canPulse & pgt_1Hz_out;

timerAndControlInput U0(.keypad(keypad),.enablen(mag_on),.clk(clock),.loadn(loadn_out),.pgt_1Hz(pgt_1Hz_out),.D(D_out));
mag_on U1(.STARTN(startn),.STOPN(stopn),.CLEARN(clearn),.DOOR(door_closed),.timer_done(zero_out),.mag(mag_on));
timerminseg U2(.data(D_out),.loadn(loadn_out),.clrn(clearn),.clock(pgt_1Hz_out_canPulse),.enable(mag_on),.zero(zero_out),.sec_ones(sec_ones_out),.sec_tens(sec_tens_out),.mins(mins_out));
bcd_7segmentos U3(.sec_ones(sec_ones_out),.sec_tens(sec_tens_out),.mins(mins_out),.sec_ones_segs(sec_ones_segs),.sec_tens_segs(sec_tens_segs),.min_segs(min_segs));

always @(negedge clearn) begin// o microondas só voltará a funcionar caso seja dado um clear nele
	canPulse<=1;
	count<=1;
end

always @( posedge zero_out) begin// bloqueia o incremento das variáveis sec_tens e sec_mins que ocorriam por engano e faziam com que o microondas fosse ativado novamente mesmo após o término do tempo
	canPulse =(count==1)?0:1; //necessito da troca "instantânea" dessa variável. por isso a atribuição bloqueante
	count<=~count;
end
endmodule

microondas/microwaveOven_tb.v
`timescale 1ms/1ms
module microwaveOven_tb();
reg [9:0]keypad_tb;
reg startn_tb=1,stopn_tb,clearn_tb,door_closed_tb,clock_tb=0;
wire mag_on_tb;
wire [6:0] sec_ones_segs_tb,sec_tens_segs_tb,min_segs_tb;
integer i;
microwaveOven DUT(.keypad(keypad_tb),.startn(startn_tb),.stopn(stopn_tb),.clearn(clearn_tb),.door_closed(door_closed_tb),.clock(clock_tb),.mag_on(mag_on_tb),.sec_ones_segs(sec_ones_segs_tb),.sec_tens_segs(sec_tens_segs_tb),.min_segs(min_segs_tb));
initial begin
	$dumpfile("microwaveOven_tb.vcd");
	$dumpvars(0,microwaveOven_tb);
	i=0;
	//tentativa de inserir digitos para a primeira contagem
	keypad_tb=10'b0000000100;//2
	#110;
	keypad_tb=10'b0000000001;//0
	#84;
	keypad_tb=10'b0001000000;//6
	#10;
	keypad_tb=10'b0000000000;// um valor inválido para evitar ficar colocando o numero 6 o tempo todo. Na prática outros valores não seriam inseridos acidentalmete porque esses dígitos só são válidos durante o pressionar do keypad
	// testando a contagem decrescente 
	#200;
	{startn_tb,stopn_tb,clearn_tb,door_closed_tb}=4'b0111;
	#180000;//3 minutos
	clearn_tb=0;// reset para voltar a inserir dígitos. No entanto, o start ainda está habilitado. Por conta disso, ele irá novamente decrementar começando de 9:59 até 0:00 novamente e parará até outro pulso de reset. Na prática, o start seria desabilitado ao darmos um reset para evitar a ativação acidental como ocorre
	#20;
	clearn_tb=1;
	#1;
end


always
	#5 clock_tb=~clock_tb;

initial//14:43 aproximadamente de minutos de funcionamento do microondas
	#883035 $finish;

endmodule

/*
0000000100//2
0000000001//0
0001000000//6

microondas/microwaveOven_tb.vcd
$date
	Fri Apr 30 01:24:22 2021
$end
$version
	Icarus Verilog
$end
$timescale
	1ms
$end
$scope module microwaveOven_tb $end
$var wire 7 ! sec_tens_segs_tb [6:0] $end
$var wire 7 " sec_ones_segs_tb [6:0] $end
$var wire 7 # min_segs_tb [6:0] $end
$var wire 1 $ mag_on_tb $end
$var reg 1 % clearn_tb $end
$var reg 1 & clock_tb $end
$var reg 1 ' door_closed_tb $end
$var reg 10 ( keypad_tb [9:0] $end
$var reg 1 ) startn_tb $end
$var reg 1 * stopn_tb $end
$var integer 32 + i [31:0] $end
$scope module DUT $end
$var wire 1 % clearn $end
$var wire 1 & clock $end
$var wire 1 ' door_closed $end
$var wire 10 , keypad [9:0] $end
$var wire 1 - pgt_1Hz_out_canPulse $end
$var wire 1 ) startn $end
$var wire 1 * stopn $end
$var wire 1 . zero_out $end
$var wire 7 / sec_tens_segs [6:0] $end
$var wire 4 0 sec_tens_out [3:0] $end
$var wire 7 1 sec_ones_segs [6:0] $end
$var wire 4 2 sec_ones_out [3:0] $end
$var wire 1 3 pgt_1Hz_out $end
$var wire 4 4 mins_out [3:0] $end
$var wire 7 5 min_segs [6:0] $end
$var wire 1 $ mag_on $end
$var wire 1 6 loadn_out $end
$var wire 4 7 D_out [3:0] $end
$var reg 1 8 canPulse $end
$var reg 1 9 count $end
$scope module U0 $end
$var wire 1 & clk $end
$var wire 10 : keypad [9:0] $end
$var wire 1 3 pgt_1Hz $end
$var wire 1 6 loadn $end
$var wire 1 ; inB $end
$var wire 1 < inA $end
$var wire 1 $ enablen $end
$var wire 4 = D [3:0] $end
$scope module U0 $end
$var wire 1 & clk $end
$var reg 1 ; clk100 $end
$var reg 6 > count [5:0] $end
$upscope $end
$scope module U1 $end
$var wire 10 ? keypad [9:0] $end
$var wire 1 $ enablen $end
$var reg 1 6 dataVal $end
$var reg 4 @ out [3:0] $end
$upscope $end
$scope module U2 $end
$var wire 1 6 clear $end
$var wire 1 & clk $end
$var reg 3 A count [2:0] $end
$var reg 1 < key $end
$upscope $end
$scope module U3 $end
$var wire 1 < inA $end
$var wire 1 ; inB $end
$var wire 1 3 pgt_1Hz $end
$var wire 1 $ sel $end
$upscope $end
$upscope $end
$scope module U1 $end
$var wire 1 % CLEARN $end
$var wire 1 ' DOOR $end
$var wire 1 B RESET $end
$var wire 1 C SET $end
$var wire 1 ) STARTN $end
$var wire 1 * STOPN $end
$var wire 1 $ mag $end
$var wire 1 D nq $end
$var wire 1 . timer_done $end
$upscope $end
$scope module U2 $end
$var wire 1 - clock $end
$var wire 1 % clrn $end
$var wire 4 E data [3:0] $end
$var wire 1 $ enable $end
$var wire 1 6 loadn $end
$var wire 1 F tcSecTenstoMins $end
$var wire 1 . zero $end
$var wire 1 G zeroSecTens $end
$var wire 1 H zeroSecOnes $end
$var wire 1 I zeroMins $end
$var wire 1 J tcSecTens $end
$var wire 1 K tcSecOnes $end
$var wire 1 L tcMins $end
$var wire 4 M sec_tens [3:0] $end
$var wire 4 N sec_ones [3:0] $end
$var wire 4 O mins [3:0] $end
$scope module U0 $end
$var wire 1 % clearneg $end
$var wire 1 - clk $end
$var wire 4 P data [3:0] $end
$var wire 1 $ en $end
$var wire 1 6 loadneg $end
$var reg 4 Q out [3:0] $end
$var reg 1 K tc $end
$var reg 1 H zero $end
$upscope $end
$scope module U1 $end
$var wire 1 % clearneg $end
$var wire 1 - clk $end
$var wire 4 R data [3:0] $end
$var wire 1 K en $end
$var wire 1 6 loadneg $end
$var reg 4 S out [3:0] $end
$var reg 1 J tc $end
$var reg 1 G zero $end
$upscope $end
$scope module U2 $end
$var wire 1 % clearneg $end
$var wire 1 - clk $end
$var wire 4 T data [3:0] $end
$var wire 1 F en $end
$var wire 1 6 loadneg $end
$var reg 4 U out [3:0] $end
$var reg 1 L tc $end
$var reg 1 I zero $end
$upscope $end
$upscope $end
$scope module U3 $end
$var wire 4 V mins [3:0] $end
$var wire 4 W sec_ones [3:0] $end
$var wire 4 X sec_tens [3:0] $end
$var reg 7 Y min_segs [6:0] $end
$var reg 7 Z sec_ones_segs [6:0] $end
$var reg 7 [ sec_tens_segs [6:0] $end
$upscope $end
$upscope $end
$upscope $end
$enddefinitions $end
#0
$dumpvars
b1 [
b1 Z
b1 Y
b0 X
b0 W
b0 V
b0 U
b0 T
b0 S
b0 R
b0 Q
b10 P
b0 O
b0 N
b0 M
0L
0K
0J
1I
1H
1G
0F
b10 E
1D
0C
1B
b0 A
b10 @
b100 ?
b0 >
b10 =
0<
0;
b100 :
19
18
b10 7
06
b1 5
b0 4
03
b0 2
b1 1
b0 0
b1 /
1.
0-
b100 ,
b0 +
x*
1)
b100 (
x'
0&
x%
0$
b1 #
b1 "
b1 !
$end
#5
b1 >
b1 A
1&
#10
0&
#15
b10 >
b10 A
1&
#20
0&
#25
b11 >
b11 A
1&
#30
0&
#35
0.
b10010 "
b10010 1
b10010 Z
0H
b10 2
b10 N
b10 Q
b10 R
b10 W
1-
13
b100 >
b100 A
1<
1&
#40
0&
#45
b101 >
b101 A
1&
#50
0&
#55
b110 >
b110 A
1&
#60
0&
#65
0-
03
b111 >
b111 A
0<
1&
#70
0&
#75
b1000 >
b0 A
1&
#80
0&
#85
b1001 >
b1 A
1&
#90
0&
#95
b1010 >
b10 A
1&
#100
0&
#105
b1011 >
b11 A
1&
#110
b0 7
b0 =
b0 @
b0 E
b0 P
0&
b1 (
b1 ,
b1 :
b1 ?
#115
b1 "
b1 1
b1 Z
b10010 !
b10010 /
b10010 [
0G
b10 0
b10 M
b10 S
b10 T
b10 X
1H
b0 2
b0 N
b0 Q
b0 R
b0 W
1-
13
b1100 >
b100 A
1<
1&
#120
0&
#125
b1101 >
b101 A
1&
#130
0&
#135
b1110 >
b110 A
1&
#140
0&
#145
0-
03
b1111 >
b111 A
0<
1&
#150
0&
#155
b10000 >
b0 A
1&
#160
0&
#165
b10001 >
b1 A
1&
#170
0&
#175
b10010 >
b10 A
1&
#180
0&
#185
b10011 >
b11 A
1&
#190
0&
#194
b110 7
b110 =
b110 @
b110 E
b110 P
b1000000 (
b1000000 ,
b1000000 :
b1000000 ?
#195
b100000 "
b100000 1
b100000 Z
b1 !
b1 /
b1 [
b10010 #
b10010 5
b10010 Y
0H
b110 2
b110 N
b110 Q
b110 R
b110 W
1G
b0 0
b0 M
b0 S
b0 T
b0 X
0I
b10 4
b10 O
b10 U
b10 V
1-
13
b10100 >
b100 A
1<
1&
#200
0&
#204
0-
03
0<
b101 A
16
bx 7
bx =
bx @
bx E
bx P
b0 (
b0 ,
b0 :
b0 ?
#205
b10101 >
b110 A
1&
#210
0&
#215
b10110 >
b111 A
1&
#220
0&
#225
b10111 >
b0 A
1&
#230
0&
#235
b11000 >
b1 A
1&
#240
0&
#245
b11001 >
b10 A
1&
#250
0&
#255
b11010 >
b11 A
1&
#260
0&
#265
1-
13
b11011 >
1<
b100 A
1&
#270
0&
#275
0-
03
b11100 >
0<
b101 A
1&
#280
0&
#285
b11101 >
b110 A
1&
#290
0&
#295
b11110 >
b111 A
1&
#300
0&
#305
b11111 >
b0 A
1&
#310
0&
#315
b100000 >
b1 A
1&
#320
0&
#325
b100001 >
b10 A
1&
#330
0&
#335
b100010 >
b11 A
1&
#340
0&
#345
1-
13
b100011 >
1<
b100 A
1&
#350
0&
#355
0-
03
b100100 >
0<
b101 A
1&
#360
0&
#365
b100101 >
b110 A
1&
#370
0&
#375
b100110 >
b111 A
1&
#380
0&
#385
b100111 >
b0 A
1&
#390
0&
#395
b101000 >
b1 A
1&
#400
0&
#404
1$
0D
1C
0B
0)
1*
1%
1'
#405
b101001 >
b10 A
1&
#410
0&
#415
b101010 >
b11 A
1&
#420
0&
#425
b101011 >
1<
b100 A
1&
#430
0&
#435
b101100 >
0<
b101 A
1&
#440
0&
#445
b101101 >
b110 A
1&
#450
0&
#455
b101110 >
b111 A
1&
#460
0&
#465
b101111 >
b0 A
1&
#470
0&
#475
b110000 >
b1 A
1&
#480
0&
#485
b110001 >
b10 A
1&
#490
0&
#495
b100100 "
b100100 1
b100100 Z
b101 2
b101 N
b101 Q
b101 R
b101 W
1-
13
1;
b0 >
b11 A
1&
#500
0&
#505
b1 >
1<
b100 A
1&
#510
0&
#515
b10 >
0<
b101 A
1&
#520
0&
#525
b11 >
b110 A
1&
#530
0&
#535
b100 >
b111 A
1&
#540
0&
#545
b101 >
b0 A
1&
#550
0&
#555
b110 >
b1 A
1&
#560
0&
#565
b111 >
b10 A
1&
#570
0&
#575
b1000 >
b11 A
1&
#580
0&
#585
b1001 >
1<
b100 A
1&
#590
0&
#595
b1010 >
0<
b101 A
1&
#600
0&
#605
b1011 >
b110 A
1&
#610
0&
#615
b1100 >
b111 A
1&
#620
0&
#625
b1101 >
b0 A
1&
#630
0&
#635
b1110 >
b1 A
1&
#640
0&
#645
b1111 >
b10 A
1&
#650
0&
#655
b10000 >
b11 A
1&
#660
0&
#665
b10001 >
1<
b100 A
1&
#670
0&
#675
b10010 >
0<
b101 A
1&
#680
0&
#685
b10011 >
b110 A
1&
#690
0&
#695
b10100 >
b111 A
1&
#700
0&
#705
b10101 >
b0 A
1&
#710
0&
#715
b10110 >
b1 A
1&
#720
0&
#725
b10111 >
b10 A
1&
#730
0&
#735
b11000 >
b11 A
1&
#740
0&
#745
b11001 >
1<
b100 A
1&
#750
0&
#755
b11010 >
0<
b101 A
1&
#760
0&
#765
b11011 >
b110 A
1&
#770
0&
#775
b11100 >
b111 A
1&
#780
0&
#785
b11101 >
b0 A
1&
#790
0&
#795
b11110 >
b1 A
1&
#800
0&
#805
b11111 >
b10 A
1&
#810
0&
#815
b100000 >
b11 A
1&
#820
0&
#825
b100001 >
1<
b100 A
1&
#830
0&
#835
b100010 >
0<
b101 A
1&
#840
0&
#845
b100011 >
b110 A
1&
#850
0&
#855
b100100 >
b111 A
1&
#860
0&
#865
b100101 >
b0 A
1&
#870
0&
#875
b100110 >
b1 A
1&
#880
0&
#885
b100111 >
b10 A
1&
#890
0&
#895
b101000 >
b11 A
1&
#900
0&
#905
b101001 >
1<
b100 A
1&
#910
0&
#915
b101010 >
0<
b101 A
1&
#920
0&
#925
b101011 >
b110 A
1&
#930
0&
#935
b101100 >
b111 A
1&
#940
0&
#945
b101101 >
b0 A
1&
#950
0&
#955
b101110 >
b1 A
1&
#960
0&
#965
b101111 >
b10 A
1&
#970
0&
#975
b110000 >
b11 A
1&
#980
0&
#985
b110001 >
1<
b100 A
1&
#990
0&
#995
0-
03
0;
b0 >
0<
b101 A
1&
#1000
0&
#1005
b1 >
b110 A
1&
#1010
0&
#1015
b10 >
b111 A
1&
#1020
0&
#1025
b11 >
b0 A
1&
#1030
0&
#1035
b100 >
b1 A
1&
#1040
0&
#1045
b101 >
b10 A
1&
#1050
0&
#1055
b110 >
b11 A
1&
#1060
0&
#1065
b111 >
1<
b100 A
1&
#1070
0&
#1075
b1000 >
0<
b101 A
1&
#1080
0&
#1085
b1001 >
b110 A
1&
#1090
0&
#1095
b1010 >
b111 A
1&
#1100
0&
#1105
b1011 >
b0 A
1&
#1110
0&
#1115
b1100 >
b1 A
1&
#1120
0&
#1125
b1101 >
b10 A
1&
#1130
0&
#1135
b1110 >
b11 A
1&
#1140
0&
#1145
b1111 >
1<
b100 A
1&
#1150
0&
#1155
b10000 >
0<
b101 A
1&
#1160
0&
#1165
b10001 >
b110 A
1&
#1170
0&
#1175
b10010 >
b111 A
1&
#1180
0&
#1185
b10011 >
b0 A
1&
#1190
0&
#1195
b10100 >
b1 A
1&
#1200
0&
#1205
b10101 >
b10 A
1&
#1210
0&
#1215
b10110 >
b11 A
1&
#1220
0&
#1225
b10111 >
1<
b100 A
1&
#1230
0&
#1235
b11000 >
0<
b101 A
1&
#1240
0&
#1245
b11001 >
b110 A
1&
#1250
0&
#1255
b11010 >
b111 A
1&
#1260
0&
#1265
b11011 >
b0 A
1&
#1270
0&
#1275
b11100 >
b1 A
1&
#1280
0&
#1285
b11101 >
b10 A
1&
#1290
0&
#1295
b11110 >
b11 A
1&
#1300
0&
#1305
b11111 >
1<
b100 A
1&
#1310
0&
#1315
b100000 >
0<
b101 A
1&
#1320
0&
#1325
b100001 >
b110 A
1&
#1330
0&
#1335
b100010 >
b111 A
1&
#1340
0&
#1345
b100011 >
b0 A
1&
#1350
0&
#1355
b100100 >
b1 A
1&
#1360
0&
#1365
b100101 >
b10 A
1&
#1370
0&
#1375
b100110 >
b11 A
1&
#1380
0&
#1385
b100111 >
1<
b100 A
1&
#1390
0&
#1395
b101000 >
0<
b101 A
1&
#1400
0&
#1405
b101001 >
b110 A
1&
#1410
0&
#1415
b101010 >
b111 A
1&
#1420
0&
#1425
b101011 >
b0 A
1&
#1430
0&
#1435
b101100 >
b1 A
1&
#1440
0&
#1445
b101101 >
b10 A
1&
#1450
0&
#1455
b101110 >
b11 A
1&
#1460
0&
#1465
b101111 >
1<
b100 A
1&
#1470
0&
#1475
b110000 >
0<
b101 A
1&
#1480
0&
#1485
b110001 >
b110 A
1&
#1490
0&
#1495
b1001100 "
b1001100 1
b1001100 Z
b100 2
b100 N
b100 Q
b100 R
b100 W
1-
13
1;
b0 >
b111 A
1&
#1500
0&
#1505
b1 >
b0 A
1&
#1510
0&
#1515
b10 >
b1 A
1&
#1520
0&
#1525
b11 >
b10 A
1&
#1530
0&
#1535
b100 >
b11 A
1&
#1540
0&
#1545
b101 >
1<
b100 A
1&
#1550
0&
#1555
b110 >
0<
b101 A
1&
#1560
0&
#1565
b111 >
b110 A
1&
#1570
0&
#1575
b1000 >
b111 A
1&
#1580
0&
#1585
b1001 >
b0 A
1&
#1590
0&
#1595
b1010 >
b1 A
1&
#1600
0&
#1605
b1011 >
b10 A
1&
#1610
0&
#1615
b1100 >
b11 A
1&
#1620
0&
#1625
b1101 >
1<
b100 A
1&
#1630
0&
#1635
b1110 >
0<
b101 A
1&
#1640
0&
#1645
b1111 >
b110 A
1&
#1650
0&
#1655
b10000 >
b111 A
1&
#1660
0&
#1665
b10001 >
b0 A
1&
#1670
0&
#1675
b10010 >
b1 A
1&
#1680
0&
#1685
b10011 >
b10 A
1&
#1690
0&
#1695
b10100 >
b11 A
1&
#1700
0&
#1705
b10101 >
1<
b100 A
1&
#1710
0&
#1715
b10110 >
0<
b101 A
1&
#1720
0&
#1725
b10111 >
b110 A
1&
#1730
0&
#1735
b11000 >
b111 A
1&
#1740
0&
#1745
b11001 >
b0 A
1&
#1750
0&
#1755
b11010 >
b1 A
1&
#1760
0&
#1765
b11011 >
b10 A
1&
#1770
0&
#1775
b11100 >
b11 A
1&
#1780
0&
#1785
b11101 >
1<
b100 A
1&
#1790
0&
#1795
b11110 >
0<
b101 A
1&
#1800
0&
#1805
b11111 >
b110 A
1&
#1810
0&
#1815
b100000 >
b111 A
1&
#1820
0&
#1825
b100001 >
b0 A
1&
#1830
0&
#1835
b100010 >
b1 A
1&
#1840
0&
#1845
b100011 >
b10 A
1&
#1850
0&
#1855
b100100 >
b11 A
1&
#1860
0&
#1865
b100101 >
1<
b100 A
1&
#1870
0&
#1875
b100110 >
0<
b101 A
1&
#1880
0&
#1885
b100111 >
b110 A
1&
#1890
0&
#1895
b101000 >
b111 A
1&
#1900
0&
#1905
b101001 >
b0 A
1&
#1910
0&
#1915
b101010 >
b1 A
1&
#1920
0&
#1925
b101011 >
b10 A
1&
#1930
0&
#1935
b101100 >
b11 A
1&
#1940
0&
#1945
b101101 >
1<
b100 A
1&
#1950
0&
#1955
b101110 >
0<
b101 A
1&
#1960
0&
#1965
b101111 >
b110 A
1&
#1970
0&
#1975
b110000 >
b111 A
1&
#1980
0&
#1985
b110001 >
b0 A
1&
#1990
0&
#1995
0-
03
0;
b0 >
b1 A
1&
#2000
0&
#2005
b1 >
b10 A
1&
#2010
0&
#2015
b10 >
b11 A
1&
#2020
0&
#2025
b11 >
1<
b100 A
1&
#2030
0&
#2035
b100 >
0<
b101 A
1&
#2040
0&
#2045
b101 >
b110 A
1&
#2050
0&
#2055
b110 >
b111 A
1&
#2060
0&
#2065
b111 >
b0 A
1&
#2070
0&
#2075
b1000 >
b1 A
1&
#2080
0&
#2085
b1001 >
b10 A
1&
#2090
0&
#2095
b1010 >
b11 A
1&
#2100
0&
#2105
b1011 >
1<
b100 A
1&
#2110
0&
#2115
b1100 >
0<
b101 A
1&
#2120
0&
#2125
b1101 >
b110 A
1&
#2130
0&
#2135
b1110 >
b111 A
1&
#2140
0&
#2145
b1111 >
b0 A
1&
#2150
0&
#2155
b10000 >
b1 A
1&
#2160
0&
#2165
b10001 >
b10 A
1&
#2170
0&
#2175
b10010 >
b11 A
1&
#2180
0&
#2185
b10011 >
1<
b100 A
1&
#2190
0&
#2195
b10100 >
0<
b101 A
1&
#2200
0&
#2205
b10101 >
b110 A
1&
#2210
0&
#2215
b10110 >
b111 A
1&
#2220
0&
#2225
b10111 >
b0 A
1&
#2230
0&
#2235
b11000 >
b1 A
1&
#2240
0&
#2245
b11001 >
b10 A
1&
#2250
0&
#2255
b11010 >
b11 A
1&
#2260
0&
#2265
b11011 >
1<
b100 A
1&
#2270
0&
#2275
b11100 >
0<
b101 A
1&
#2280
0&
#2285
b11101 >
b110 A
1&
#2290
0&
#2295
b11110 >
b111 A
1&
#2300
0&
#2305
b11111 >
b0 A
1&
#2310
0&
#2315
b100000 >
b1 A
1&
#2320
0&
#2325
b100001 >
b10 A
1&
#2330
0&
#2335
b100010 >
b11 A
1&
#2340
0&
#2345
b100011 >
1<
b100 A
1&
#2350
0&
#2355
b100100 >
0<
b101 A
1&
#2360
0&
#2365
b100101 >
b110 A
1&
#2370
0&
#2375
b100110 >
b111 A
1&
#2380
0&
#2385
b100111 >
b0 A
1&
#2390
0&
#2395
b101000 >
b1 A
1&
#2400
0&
#2405
b101001 >
b10 A
1&
#2410
0&
#2415
b101010 >
b11 A
1&
#2420
0&
#2425
b101011 >
1<
b100 A
1&
#2430
0&
#2435
b101100 >
0<
b101 A
1&
#2440
0&
#2445
b101101 >
b110 A
1&
#2450
0&
#2455
b101110 >
b111 A
1&
#2460
0&
#2465
b101111 >
b0 A
1&
#2470
0&
#2475
b110000 >
b1 A
1&
#2480
0&
#2485
b110001 >
b10 A
1&
#2490
0&
#2495
b110 "
b110 1
b110 Z
b11 2
b11 N
b11 Q
b11 R
b11 W
1-
13
1;
b0 >
b11 A
1&
#2500
0&
#2505
b1 >
1<
b100 A
1&
#2510
0&
#2515
b10 >
0<
b101 A
1&
#2520
0&
#2525
b11 >
b110 A
1&
#2530
0&
#2535
b100 >
b111 A
1&
#2540
0&
#2545
b101 >
b0 A
1&
#2550
0&
#2555
b110 >
b1 A
1&
#2560
0&
#2565
b111 >
b10 A
1&
#2570
0&
#2575
b1000 >
b11 A
1&
#2580
0&
#2585
b1001 >
1<
b100 A
1&
#2590
0&
#2595
b1010 >
0<
b101 A
1&
#2600
0&
