timer min seg/contadormod10.v
module contadormod10(input wire [3:0] data, input wire loadneg,clearneg,clk,en,output reg [3:0] out,output reg tc,zero);
initial begin
	out<=0;
	zero<=1;
	tc<=0;
end
always @(posedge clk or negedge clearneg) begin
	if(!clearneg)begin
		out<=0; zero<=1; tc<=1;
	end
	else if(!loadneg)begin
		out<=data; zero<=(data==0)?1:0;
	end
	else begin
		if(en) begin
			out<=out-1;
			case(out)
				4'b0001:begin zero<=1; tc<=1; end// esta definido no 1 porque a alteração so ocorre no próximo pulso de clock
				4'b0000:begin out<=9;zero<=0; tc<=0; end// explicação análoga a da linha acima
				default:begin zero<=0; tc<=0; end
			endcase
		end
		else begin
			out<=out; tc<=0; 
		end
	end
end
endmodule

timer min seg/contadormod6.v
module contadormod6(input wire [3:0] data, input wire loadneg,clearneg,clk,en,output reg [3:0] out,output reg tc,zero);
initial begin
	out<=0;
	zero<=1;
	tc<=0;
end
always @(posedge clk or negedge clearneg) begin
	if(!clearneg)begin
		out<=0; zero<=1; tc<=1;
	end
	else if(!loadneg)begin
		out<=data; zero<=(data==0)?1:0;
	end
	else begin
		if(en) begin
			out<=out-1;
			case(out)
				4'b0001:begin zero<=1; tc<=1; end// esta definido no 1 porque a alteração so ocorre no proximo pulso de clock
				4'b0000:begin out<=5;zero<=0; tc<=0; end// explicação análoga a da linha acima
				default:begin zero<=0; tc<=0; end
			endcase
		end
		else begin
			out<=out; tc<=0; 
		end
	end
end
endmodule

microondas/timerminseg.v
module timerminseg(input wire [3:0] data, input wire loadn,clrn,clock,enable,output wire zero,output wire [3:0] sec_ones,sec_tens,mins);

wire tcSecOnes,tcSecTens,tcMins,zeroSecOnes,zeroSecTens,zeroMins;
wire tcSecTenstoMins;// feito por conta do minuto estar sendo decrementado na hora errada. agora só decrementa quando os segundos terminarem
assign tcSecTenstoMins=zeroSecOnes&zeroSecTens&tcSecOnes; 
contadormod10 U0 (.data(data),.loadneg(loadn),.clearneg(clrn),.clk(clock),.en(enable),.tc(tcSecOnes),.zero(zeroSecOnes),.out(sec_ones));
contadormod6 U1 (.data(sec_ones),.loadneg(loadn),.clearneg(clrn),.clk(clock),.en(tcSecOnes),.tc(tcSecTens),.zero(zeroSecTens),.out(sec_tens));
contadormod10 U2 (.data(sec_tens),.loadneg(loadn),.clearneg(clrn),.clk(clock),.en(tcSecTenstoMins),.tc(tcMins),.zero(zeroMins),.out(mins));
assign zero =  zeroSecOnes & zeroSecTens & zeroMins;

endmodule

timer min seg/timerminseg_tb.v
`timescale 1ms/1ms
module timerminseg_tb();
reg[3:0] data_tb;
reg loadn_tb=1,clrn_tb=1,clock_tb=0,enable_tb;
wire [3:0] sec_ones_tb,sec_tens_tb,mins_tb;
wire zero_tb;
timerminseg DUT (.data(data_tb),.loadn(loadn_tb),.clrn(clrn_tb),.clock(clock_tb),.enable(enable_tb),.sec_ones(sec_ones_tb),.sec_tens(sec_tens_tb),.mins(mins_tb),.zero(zero_tb));
initial begin
	$dumpfile("timerminseg_tb.vcd");
	$dumpvars(0,timerminseg_tb);
	enable_tb=0;
	data_tb=2; loadn_tb=0;
	#20;
	loadn_tb=1;
	#20;
	data_tb=0; loadn_tb=0;
	#20;
	loadn_tb=1;
	#20;
	data_tb=6; loadn_tb=0;
	#20;
	loadn_tb=1;
	#40;
	enable_tb=1;
	#356;
	clrn_tb=0;
	#10;
	clrn_tb=1;
	#346;
	enable_tb=0;



	
end

always 
	#5 clock_tb=~clock_tb;


initial
	#50000 $finish;
endmodule

timer min seg/timerminseg_tb.vcd
$date
	Thu Apr 29 19:56:21 2021
$end
$version
	Icarus Verilog
$end
$timescale
	1ms
$end
$scope module timerminseg_tb $end
$var wire 1 ! zero_tb $end
$var wire 4 " sec_tens_tb [3:0] $end
$var wire 4 # sec_ones_tb [3:0] $end
$var wire 4 $ mins_tb [3:0] $end
$var reg 1 % clock_tb $end
$var reg 1 & clrn_tb $end
$var reg 4 ' data_tb [3:0] $end
$var reg 1 ( enable_tb $end
$var reg 1 ) loadn_tb $end
$scope module DUT $end
$var wire 1 % clock $end
$var wire 1 & clrn $end
$var wire 4 * data [3:0] $end
$var wire 1 ( enable $end
$var wire 1 ) loadn $end
$var wire 1 + tcSecTenstoMins $end
$var wire 1 ! zero $end
$var wire 1 , zeroSecTens $end
$var wire 1 - zeroSecOnes $end
$var wire 1 . zeroMins $end
$var wire 1 / tcSecTens $end
$var wire 1 0 tcSecOnes $end
$var wire 1 1 tcMins $end
$var wire 4 2 sec_tens [3:0] $end
$var wire 4 3 sec_ones [3:0] $end
$var wire 4 4 mins [3:0] $end
$scope module U0 $end
$var wire 1 & clearneg $end
$var wire 1 % clk $end
$var wire 4 5 data [3:0] $end
$var wire 1 ( en $end
$var wire 1 ) loadneg $end
$var reg 4 6 out [3:0] $end
$var reg 1 0 tc $end
$var reg 1 - zero $end
$upscope $end
$scope module U1 $end
$var wire 1 & clearneg $end
$var wire 1 % clk $end
$var wire 4 7 data [3:0] $end
$var wire 1 0 en $end
$var wire 1 ) loadneg $end
$var reg 4 8 out [3:0] $end
$var reg 1 / tc $end
$var reg 1 , zero $end
$upscope $end
$scope module U2 $end
$var wire 1 & clearneg $end
$var wire 1 % clk $end
$var wire 4 9 data [3:0] $end
$var wire 1 + en $end
$var wire 1 ) loadneg $end
$var reg 4 : out [3:0] $end
$var reg 1 1 tc $end
$var reg 1 . zero $end
$upscope $end
$upscope $end
$upscope $end
$enddefinitions $end
#0
$dumpvars
b0 :
b0 9
b0 8
b0 7
b0 6
b10 5
b0 4
b0 3
b0 2
01
00
0/
1.
1-
1,
0+
b10 *
0)
0(
b10 '
1&
0%
b0 $
b0 #
b0 "
1!
$end
#5
0!
0-
b10 #
b10 3
b10 6
b10 7
1%
#10
0%
#15
0,
b10 "
b10 2
b10 8
b10 9
1%
#20
0%
1)
#25
1%
#30
0%
#35
1%
#40
0%
0)
b0 '
b0 *
b0 5
#45
1-
b0 #
b0 3
b0 6
b0 7
0.
b10 $
b10 4
b10 :
1%
#50
0%
#55
1,
b0 "
b0 2
b0 8
b0 9
1%
#60
0%
1)
#65
1%
#70
0%
#75
1%
#80
0%
0)
b110 '
b110 *
b110 5
#85
0!
0-
b110 #
b110 3
b110 6
b110 7
1.
b0 $
b0 4
b0 :
1%
#90
0%
#95
0,
b110 "
b110 2
b110 8
b110 9
1%
#100
0%
1)
#105
1%
#110
0%
#115
1%
#120
0%
#125
1%
#130
0%
#135
1%
#140
0%
1(
#145
b101 #
b101 3
b101 6
b101 7
1%
#150
0%
#155
b100 #
b100 3
b100 6
b100 7
1%
#160
0%
#165
b11 #
b11 3
b11 6
b11 7
1%
#170
0%
#175
b10 #
b10 3
b10 6
b10 7
1%
#180
0%
#185
b1 #
b1 3
b1 6
b1 7
1%
#190
0%
#195
10
1-
b0 #
b0 3
b0 6
b0 7
1%
#200
0%
#205
00
0-
b1001 #
b1001 3
b1001 6
b1001 7
b101 "
b101 2
b101 8
b101 9
1%
#210
0%
#215
b1000 #
b1000 3
b1000 6
b1000 7
1%
#220
0%
#225
b111 #
b111 3
b111 6
b111 7
1%
#230
0%
#235
b110 #
b110 3
b110 6
b110 7
1%
#240
0%
#245
b101 #
b101 3
b101 6
b101 7
1%
#250
0%
#255
b100 #
b100 3
b100 6
b100 7
1%
#260
0%
#265
b11 #
b11 3
b11 6
b11 7
1%
#270
0%
#275
b10 #
b10 3
b10 6
b10 7
1%
#280
0%
#285
b1 #
b1 3
b1 6
b1 7
1%
#290
0%
#295
10
1-
b0 #
b0 3
b0 6
b0 7
1%
#300
0%
#305
00
0-
b1001 #
b1001 3
b1001 6
b1001 7
b100 "
b100 2
b100 8
b100 9
1%
#310
0%
#315
b1000 #
b1000 3
b1000 6
b1000 7
1%
#320
0%
#325
b111 #
b111 3
b111 6
b111 7
1%
#330
0%
#335
b110 #
b110 3
b110 6
b110 7
1%
#340
0%
#345
b101 #
b101 3
b101 6
b101 7
1%
#350
0%
#355
b100 #
b100 3
b100 6
b100 7
1%
#360
0%
#365
b11 #
b11 3
b11 6
b11 7
1%
#370
0%
#375
b10 #
b10 3
b10 6
b10 7
1%
#380
0%
#385
b1 #
b1 3
b1 6
b1 7
1%
#390
0%
#395
10
1-
b0 #
b0 3
b0 6
b0 7
1%
#400
0%
#405
00
0-
b1001 #
b1001 3
b1001 6
b1001 7
b11 "
b11 2
b11 8
b11 9
1%
#410
0%
#415
b1000 #
b1000 3
b1000 6
b1000 7
1%
#420
0%
#425
b111 #
b111 3
b111 6
b111 7
1%
#430
0%
#435
b110 #
b110 3
b110 6
b110 7
1%
#440
0%
#445
b101 #
b101 3
b101 6
b101 7
1%
#450
0%
#455
b100 #
b100 3
b100 6
b100 7
1%
#460
0%
#465
b11 #
b11 3
b11 6
b11 7
1%
#470
0%
#475
b10 #
b10 3
b10 6
b10 7
1%
#480
0%
#485
b1 #
b1 3
b1 6
b1 7
1%
#490
0%
#495
10
1-
b0 #
b0 3
b0 6
b0 7
1%
#496
1!
1+
1/
1,
b0 "
b0 2
b0 8
b0 9
11
0&
#500
0%
#505
1%
#506
1&
#510
0%
#515
0+
0!
00
0-
b1001 #
b1001 3
b1001 6
b1001 7
0/
0,
b101 "
b101 2
b101 8
b101 9
01
0.
b1001 $
b1001 4
b1001 :
1%
#520
0%
#525
b1000 #
b1000 3
b1000 6
b1000 7
1%
#530
0%
#535
b111 #
b111 3
b111 6
b111 7
1%
#540
0%
#545
b110 #
b110 3
b110 6
b110 7
1%
#550
0%
#555
b101 #
b101 3
b101 6
b101 7
1%
#560
0%
#565
b100 #
b100 3
b100 6
b100 7
1%
#570
0%
#575
b11 #
b11 3
b11 6
b11 7
1%
#580
0%
#585
b10 #
b10 3
b10 6
b10 7
1%
#590
0%
#595
b1 #
b1 3
b1 6
b1 7
1%
#600
0%
#605
10
1-
b0 #
b0 3
b0 6
b0 7
1%
#610
0%
#615
00
0-
b1001 #
b1001 3
b1001 6
b1001 7
b100 "
b100 2
b100 8
b100 9
1%
#620
0%
#625
b1000 #
b1000 3
b1000 6
b1000 7
1%
#630
0%
#635
b111 #
b111 3
b111 6
b111 7
1%
#640
0%
#645
b110 #
b110 3
b110 6
b110 7
1%
#650
0%
#655
b101 #
b101 3
b101 6
b101 7
1%
#660
0%
#665
b100 #
b100 3
b100 6
b100 7
1%
#670
0%
#675
b11 #
b11 3
b11 6
b11 7
1%
#680
0%
#685
b10 #
b10 3
b10 6
b10 7
1%
#690
0%
#695
b1 #
b1 3
b1 6
b1 7
1%
#700
0%
#705
10
1-
b0 #
b0 3
b0 6
b0 7
1%
#710
0%
#715
00
0-
b1001 #
b1001 3
b1001 6
b1001 7
b11 "
b11 2
b11 8
b11 9
1%
#720
0%
#725
b1000 #
b1000 3
b1000 6
b1000 7
1%
#730
0%
#735
b111 #
b111 3
b111 6
b111 7
1%
#740
0%
#745
b110 #
b110 3
b110 6
b110 7
1%
#750
0%
#755
b101 #
b101 3
b101 6
b101 7
1%
#760
0%
#765
b100 #
b100 3
b100 6
b100 7
1%
#770
0%
#775
b11 #
b11 3
b11 6
b11 7
1%
#780
0%
#785
b10 #
b10 3
b10 6
b10 7
1%
#790
0%
#795
b1 #
b1 3
b1 6
b1 7
1%
#800
0%
#805
10
1-
b0 #
b0 3
b0 6
b0 7
1%
#810
0%
#815
00
0-
b1001 #
b1001 3
b1001 6
b1001 7
b10 "
b10 2
b10 8
b10 9
1%
#820
0%
#825
b1000 #
b1000 3
b1000 6
b1000 7
1%
#830
0%
#835
b111 #
b111 3
b111 6
b111 7
1%
#840
0%
#845
b110 #
b110 3
b110 6
b110 7
1%
#850
0%
#852
0(
