timer min seg/contadormod6.v
module contadormod6(input wire [3:0] data, input wire loadneg,clearneg,clk,en,output reg [3:0] out,output reg tc,zero);
initial begin
	out<=0;
	zero<=1;
	tc<=0;
end
always @(posedge clk or negedge clearneg) begin
	if(!clearneg)begin
		out<=0; zero<=1; tc<=1;
	end
	else if(!loadneg)begin
		out<=data; zero<=(data==0)?1:0;
	end
	else begin
		if(en) begin
			out<=out-1;
			case(out)
				4'b0001:begin zero<=1; tc<=1; end// esta definido no 1 porque a alteração so ocorre no proximo pulso de clock
				4'b0000:begin out<=5;zero<=0; tc<=0; end// explicação análoga a da linha acima
				default:begin zero<=0; tc<=0; end
			endcase
		end
		else begin
			out<=out; tc<=0; 
		end
	end
end
endmodule

timer min seg/contadormod6/contadormod6_tb.v
`timescale 1ns/1ns
module contadormod6_tb();
reg [3:0] data_tb;
reg loadneg_tb=1,clearneg_tb=1,clk_tb=0,en_tb;
wire [3:0] out_tb;
wire tc_tb,zero_tb;
integer i;
contadormod6 DUT (.data(data_tb),.loadneg(loadneg_tb),.clearneg(clearneg_tb),.clk(clk_tb),.en(en_tb),.out(out_tb),.tc(tc_tb),.zero(zero_tb));
initial begin
	$dumpfile("contadormod6_tb.vcd");
	$dumpvars(0,contadormod6_tb);
	i=0;
	loadneg_tb=0; data_tb=5;
	en_tb=1;
	#200;
	data_tb=0;
	#200;
	data_tb=5;
	#200;
	loadneg_tb=1;
	#200;
	en_tb=0;
	#100;
	loadneg_tb=0; data_tb=9;
	en_tb=1;
	#10;
	loadneg_tb=1;
	#220;
	clearneg_tb=0;
	#10;
	clearneg_tb=1;
	en_tb=0;
	#50;
	en_tb=1;
end

always
	#5 clk_tb=~clk_tb;

initial
	#1000 $finish;
endmodule

timer min seg/contadormod6/contadormod6_tb.vcd
$date
	Wed Apr 28 10:41:41 2021
$end
$version
	Icarus Verilog
$end
$timescale
	1ns
$end
$scope module contadormod6_tb $end
$var wire 1 ! zero_tb $end
$var wire 1 " tc_tb $end
$var wire 4 # out_tb [3:0] $end
$var reg 1 $ clearneg_tb $end
$var reg 1 % clk_tb $end
$var reg 4 & data_tb [3:0] $end
$var reg 1 ' en_tb $end
$var reg 1 ( loadneg_tb $end
$var integer 32 ) i [31:0] $end
$scope module DUT $end
$var wire 1 $ clearneg $end
$var wire 1 % clk $end
$var wire 4 * data [3:0] $end
$var wire 1 ' en $end
$var wire 1 ( loadneg $end
$var reg 4 + out [3:0] $end
$var reg 1 " tc $end
$var reg 1 ! zero $end
$upscope $end
$upscope $end
$enddefinitions $end
#0
$dumpvars
b0 +
b101 *
b0 )
0(
1'
b101 &
0%
1$
b0 #
0"
1!
$end
#5
0!
b101 #
b101 +
1%
#10
0%
#15
1%
#20
0%
#25
1%
#30
0%
#35
1%
#40
0%
#45
1%
#50
0%
#55
1%
#60
0%
#65
1%
#70
0%
#75
1%
#80
0%
#85
1%
#90
0%
#95
1%
#100
0%
#105
1%
#110
0%
#115
1%
#120
0%
#125
1%
#130
0%
#135
1%
#140
0%
#145
1%
#150
0%
#155
1%
#160
0%
#165
1%
#170
0%
#175
1%
#180
0%
#185
1%
#190
0%
#195
1%
#200
0%
b0 &
b0 *
#205
1!
b0 #
b0 +
1%
#210
0%
#215
1%
#220
0%
#225
1%
#230
0%
#235
1%
#240
0%
#245
1%
#250
0%
#255
1%
#260
0%
#265
1%
#270
0%
#275
1%
#280
0%
#285
1%
#290
0%
#295
1%
#300
0%
#305
1%
#310
0%
#315
1%
#320
0%
#325
1%
#330
0%
#335
1%
#340
0%
#345
1%
#350
0%
#355
1%
#360
0%
#365
1%
#370
0%
#375
1%
#380
0%
#385
1%
#390
0%
#395
1%
#400
0%
b101 &
b101 *
#405
0!
b101 #
b101 +
1%
#410
0%
#415
1%
#420
0%
#425
1%
#430
0%
#435
1%
#440
0%
#445
1%
#450
0%
#455
1%
#460
0%
#465
1%
#470
0%
#475
1%
#480
0%
#485
1%
#490
0%
#495
1%
#500
0%
#505
1%
#510
0%
#515
1%
#520
0%
#525
1%
#530
0%
#535
1%
#540
0%
#545
1%
#550
0%
#555
1%
#560
0%
#565
1%
#570
0%
#575
1%
#580
0%
#585
1%
#590
0%
#595
1%
#600
0%
1(
#605
b100 #
b100 +
1%
#610
0%
#615
b11 #
b11 +
1%
#620
0%
#625
b10 #
b10 +
1%
#630
0%
#635
b1 #
b1 +
1%
#640
0%
#645
1"
1!
b0 #
b0 +
1%
#650
0%
#655
0"
0!
b101 #
b101 +
1%
#660
0%
#665
b100 #
b100 +
1%
#670
0%
#675
b11 #
b11 +
1%
#680
0%
#685
b10 #
b10 +
1%
#690
0%
#695
b1 #
b1 +
1%
#700
0%
#705
1"
1!
b0 #
b0 +
1%
#710
0%
#715
0"
0!
b101 #
b101 +
1%
#720
0%
#725
b100 #
b100 +
1%
#730
0%
#735
b11 #
b11 +
1%
#740
0%
#745
b10 #
b10 +
1%
#750
0%
#755
b1 #
b1 +
1%
#760
0%
#765
1"
1!
b0 #
b0 +
1%
#770
0%
#775
0"
0!
b101 #
b101 +
1%
#780
0%
#785
b100 #
b100 +
1%
#790
0%
#795
b11 #
b11 +
1%
#800
0%
0'
#805
1%
#810
0%
#815
1%
#820
0%
#825
1%
#830
0%
#835
1%
#840
0%
#845
1%
#850
0%
#855
1%
#860
0%
#865
1%
#870
0%
#875
1%
#880
0%
#885
1%
#890
0%
#895
1%
#900
0%
1'
b1001 &
b1001 *
0(
#905
b1001 #
b1001 +
1%
#910
0%
1(
#915
b1000 #
b1000 +
1%
#920
0%
#925
b111 #
b111 +
1%
#930
0%
#935
b110 #
b110 +
1%
#940
0%
#945
b101 #
b101 +
1%
#950
0%
#955
b100 #
b100 +
1%
#960
0%
#965
b11 #
b11 +
1%
#970
0%
#975
b10 #
b10 +
1%
#980
0%
#985
b1 #
b1 +
1%
#990
0%
#995
1"
1!
b0 #
b0 +
1%
