entrada timer e controle/mux.v
module mux(input wire sel,inA,inB,output wire pgt_1Hz);
	assign pgt_1Hz= (!sel&inA)|(sel&inB);// implementação de um mux com portas lógicas
endmodule

microondas/delaydebouncing.v
module delaydebouncing(input wire clear, clk,output reg key);
reg [2:0] count;
initial begin
	count<=0;
	key<=0;
end
always @(posedge clk or posedge clear) begin
	if (clear) begin
		count<=0;
		key<=0;
	end
	case(count)
		3'b011:begin key<=1; count<=count+1; end// considerando o 011(2)==3(10) porque a mudança só acontece após o pulso de clock
		3'b110:begin key<=0; count<=count+1; end// mesma consideração aqui
		3'b111:count<=0;
		default:count<=count+1;
	endcase
end
endmodule

entrada timer e controle/codificadorKeypadBCD/priorityEncoder.v
module priorityEncoder(input wire [9:0] keypad,input wire enablen, output reg [3:0] out,output reg dataVal);
always@* begin
	if(!enablen)begin
	    case(keypad)
	    	10'b0000000001:begin out=4'b0000; dataVal=1'b0; end
	    	10'b0000000010:begin out=4'b0001; dataVal=1'b0; end
	    	10'b0000000100:begin out=4'b0010; dataVal=1'b0; end
	    	10'b0000001000:begin out=4'b0011; dataVal=1'b0; end
	    	10'b0000010000:begin out=4'b0100; dataVal=1'b0; end
	    	10'b0000100000:begin out=4'b0101; dataVal=1'b0; end
	    	10'b0001000000:begin out=4'b0110; dataVal=1'b0; end
	    	10'b0010000000:begin out=4'b0111; dataVal=1'b0; end
	    	10'b0100000000:begin out=4'b1000; dataVal=1'b0; end
	    	10'b1000000000:begin out=4'b1001; dataVal=1'b0; end
	    	default:begin out=4'bXXXX; dataVal=1'b1; end
	    endcase
	end
	else begin
		out=4'bXXXX; dataVal=1'b1;
	end
end
endmodule

entrada timer e controle/clockdiv100/clkdiv100.v
module clkdiv100(input wire clk, output reg clk100);
reg [5:0] count;
initial begin
	clk100<=0;
	count<=0;
end
always @(posedge clk) begin
	case(count) //verifico se o contador é 49. 49 porque é necessário um clock de 1Hz(ou seja, um período de 1s compostdo de clk100=1 quando tempo=0.5s e clk100=0 quando tempo=1s)
		6'b110001:begin count<=0; clk100<=clk100^1; end// clk100 == clk100 xor 1 (o comportamento é fazer o valor de clk100 ser '1' e depois '0'). O valor binário é 49(base10)
		default:count<=count+1;
	endcase
end
endmodule

microondas/timerAndControlInput.v
module timerAndControlInput(input wire [9:0] keypad,input wire enablen,clk,output wire loadn,pgt_1Hz,output wire [3:0] D);
wire inB,inA;//conectando a saída do clock/100 ao fio inB para colocar na entrada. para o inA, é a saída dos pulsos para colocar o dígito válido no timer
clkdiv100 U0 (.clk(clk),.clk100(inB));
priorityEncoder U1 (.keypad(keypad),.enablen(enablen),.out(D),.dataVal(loadn));
delaydebouncing U2 (.clk(clk),.clear(loadn),.key(inA));
mux U3 (.sel(enablen),.inA(inA),.inB(inB),.pgt_1Hz(pgt_1Hz));

endmodule

entrada timer e controle/timerAndControlInput_tb.v
`timescale 1ms/1ms
module timerAndControlInput_tb();
reg [9:0] keypad_tb;
reg enablen_tb,clk_tb=0;
wire loadn_tb,pgt_1Hz_tb;
wire [3:0] D_tb;
integer i;
timerAndControlInput DUT(.keypad(keypad_tb),.enablen(enablen_tb),.clk(clk_tb),.loadn(loadn_tb),.pgt_1Hz(pgt_1Hz_tb),.D(D_tb));
initial begin
	$dumpfile("timerAndControlInput_tb.vcd");
	$dumpvars(0,timerAndControlInput_tb);
	keypad_tb=1;enablen_tb=0;
	repeat(10)//contando até 1024(2^10) eu consigo testar diversas vezes o bloco antes de chegar em 5 segundos
		#1000 keypad_tb=keypad_tb<<1;
	enablen_tb=1;
	keypad_tb=1;
	repeat(10)//contando até 1024(2^10) eu consigo testar diversas vezes o bloco antes de chegar em 5 segundos
		#1000 keypad_tb=keypad_tb<<1;
end

always
	#5 clk_tb=~clk_tb;//10 ms de periodo== 100Hz de freq de clock

initial
	#30000 $finish;

endmodule

entrada timer e controle/timerAndControlInput_tb.vcd
$date
	Tue Apr 27 13:08:38 2021
$end
$version
	Icarus Verilog
$end
$timescale
	1ms
$end
$scope module timerAndControlInput_tb $end
$var wire 1 ! pgt_1Hz_tb $end
$var wire 1 " loadn_tb $end
$var wire 4 # D_tb [3:0] $end
$var reg 1 $ clk_tb $end
$var reg 1 % enablen_tb $end
$var reg 10 & keypad_tb [9:0] $end
$scope module DUT $end
$var wire 1 $ clk $end
$var wire 1 % enablen $end
$var wire 10 ' keypad [9:0] $end
$var wire 1 ! pgt_1Hz $end
$var wire 1 " loadn $end
$var wire 1 ( inB $end
$var wire 1 ) inA $end
$var wire 4 * D [3:0] $end
$scope module U0 $end
$var wire 1 $ clk $end
$var reg 1 ( clk100 $end
$var reg 6 + count [5:0] $end
$upscope $end
$scope module U1 $end
$var wire 1 % enablen $end
$var wire 10 , keypad [9:0] $end
$var reg 1 " dataVal $end
$var reg 4 - out [3:0] $end
$upscope $end
$scope module U2 $end
$var wire 1 " clear $end
$var wire 1 $ clk $end
$var reg 3 . count [2:0] $end
$var reg 1 ) key $end
$upscope $end
$scope module U3 $end
$var wire 1 ) inA $end
$var wire 1 ( inB $end
$var wire 1 ! pgt_1Hz $end
$var wire 1 % sel $end
$upscope $end
$upscope $end
$upscope $end
$enddefinitions $end
#0
$dumpvars
b0 .
b0 -
b1 ,
b0 +
b0 *
0)
0(
b1 '
b1 &
0%
0$
b0 #
0"
0!
$end
#5
b1 +
b1 .
1$
#10
0$
#15
b10 +
b10 .
1$
#20
0$
#25
b11 +
b11 .
1$
#30
0$
#35
1!
b100 +
b100 .
1)
1$
#40
0$
#45
b101 +
b101 .
1$
#50
0$
#55
b110 +
b110 .
1$
#60
0$
#65
0!
b111 +
b111 .
0)
1$
#70
0$
#75
b1000 +
b0 .
1$
#80
0$
#85
b1001 +
b1 .
1$
#90
0$
#95
b1010 +
b10 .
1$
#100
0$
#105
b1011 +
b11 .
1$
#110
0$
#115
1!
b1100 +
b100 .
1)
1$
#120
0$
#125
b1101 +
b101 .
1$
#130
0$
#135
b1110 +
b110 .
1$
#140
0$
#145
0!
b1111 +
b111 .
0)
1$
#150
0$
#155
b10000 +
b0 .
1$
#160
0$
#165
b10001 +
b1 .
1$
#170
0$
#175
b10010 +
b10 .
1$
#180
0$
#185
b10011 +
b11 .
1$
#190
0$
#195
1!
b10100 +
b100 .
1)
1$
#200
0$
#205
b10101 +
b101 .
1$
#210
0$
#215
b10110 +
b110 .
1$
#220
0$
#225
0!
b10111 +
b111 .
0)
1$
#230
0$
#235
b11000 +
b0 .
1$
#240
0$
#245
b11001 +
b1 .
1$
#250
0$
#255
b11010 +
b10 .
1$
#260
0$
#265
b11011 +
b11 .
1$
#270
0$
#275
1!
b11100 +
b100 .
1)
1$
#280
0$
#285
b11101 +
b101 .
1$
#290
0$
#295
b11110 +
b110 .
1$
#300
0$
#305
0!
b11111 +
b111 .
0)
1$
#310
0$
#315
b100000 +
b0 .
1$
#320
0$
#325
b100001 +
b1 .
1$
#330
0$
#335
b100010 +
b10 .
1$
#340
0$
#345
b100011 +
b11 .
1$
#350
0$
#355
1!
b100100 +
b100 .
1)
1$
#360
0$
#365
b100101 +
b101 .
1$
#370
0$
#375
b100110 +
b110 .
1$
#380
0$
#385
0!
b100111 +
b111 .
0)
1$
#390
0$
#395
b101000 +
b0 .
1$
#400
0$
#405
b101001 +
b1 .
1$
#410
0$
#415
b101010 +
b10 .
1$
#420
0$
#425
b101011 +
b11 .
1$
#430
0$
#435
1!
b101100 +
b100 .
1)
1$
#440
0$
#445
b101101 +
b101 .
1$
#450
0$
#455
b101110 +
b110 .
1$
#460
0$
#465
0!
b101111 +
b111 .
0)
1$
#470
0$
#475
b110000 +
b0 .
1$
#480
0$
#485
b110001 +
b1 .
1$
#490
0$
#495
1(
b0 +
b10 .
1$
#500
0$
#505
b1 +
b11 .
1$
#510
0$
#515
1!
b10 +
b100 .
1)
1$
#520
0$
#525
b11 +
b101 .
1$
#530
0$
#535
b100 +
b110 .
1$
#540
0$
#545
0!
b101 +
b111 .
0)
1$
#550
0$
#555
b110 +
b0 .
1$
#560
0$
#565
b111 +
b1 .
1$
#570
0$
#575
b1000 +
b10 .
1$
#580
0$
#585
b1001 +
b11 .
1$
#590
0$
#595
1!
b1010 +
b100 .
1)
1$
#600
0$
#605
b1011 +
b101 .
1$
#610
0$
#615
b1100 +
b110 .
1$
#620
0$
#625
0!
b1101 +
b111 .
0)
1$
#630
0$
#635
b1110 +
b0 .
1$
#640
0$
#645
b1111 +
b1 .
1$
#650
0$
#655
b10000 +
b10 .
1$
#660
0$
#665
b10001 +
b11 .
1$
#670
0$
#675
1!
b10010 +
b100 .
1)
1$
#680
0$
#685
b10011 +
b101 .
1$
#690
0$
#695
b10100 +
b110 .
1$
#700
0$
#705
0!
b10101 +
b111 .
0)
1$
#710
0$
#715
b10110 +
b0 .
1$
#720
0$
#725
b10111 +
b1 .
1$
#730
0$
#735
b11000 +
b10 .
1$
#740
0$
#745
b11001 +
b11 .
1$
#750
0$
#755
1!
b11010 +
b100 .
1)
1$
#760
0$
#765
b11011 +
b101 .
1$
#770
0$
#775
b11100 +
b110 .
1$
#780
0$
#785
0!
b11101 +
b111 .
0)
1$
#790
0$
#795
b11110 +
b0 .
1$
#800
0$
#805
b11111 +
b1 .
1$
#810
0$
#815
b100000 +
b10 .
1$
#820
0$
#825
b100001 +
b11 .
1$
#830
0$
#835
1!
b100010 +
b100 .
1)
1$
#840
0$
#845
b100011 +
b101 .
1$
#850
0$
#855
b100100 +
b110 .
1$
#860
0$
#865
0!
b100101 +
b111 .
0)
1$
#870
0$
#875
b100110 +
b0 .
1$
#880
0$
#885
b100111 +
b1 .
1$
#890
0$
#895
b101000 +
b10 .
1$
#900
0$
#905
b101001 +
b11 .
1$
#910
0$
#915
1!
b101010 +
b100 .
1)
1$
#920
0$
#925
b101011 +
b101 .
1$
#930
0$
#935
b101100 +
b110 .
1$
#940
0$
#945
0!
b101101 +
b111 .
0)
1$
#950
0$
#955
b101110 +
b0 .
1$
#960
0$
#965
b101111 +
b1 .
1$
#970
0$
#975
b110000 +
b10 .
1$
#980
0$
#985
b110001 +
b11 .
1$
#990
0$
#995
1!
0(
b0 +
b100 .
1)
1$
#1000
b1 #
b1 *
b1 -
0$
b10 &
b10 '
b10 ,
#1005
b1 +
b101 .
1$
#1010
0$
#1015
b10 +
b110 .
1$
#1020
0$
#1025
0!
b11 +
b111 .
0)
1$
#1030
0$
#1035
b100 +
b0 .
1$
#1040
0$
#1045
b101 +
b1 .
1$
#1050
0$
#1055
b110 +
b10 .
1$
#1060
0$
#1065
b111 +
b11 .
1$
#1070
0$
#1075
1!
b1000 +
b100 .
1)
1$
#1080
0$
#1085
b1001 +
b101 .
1$
#1090
0$
#1095
b1010 +
b110 .
1$
#1100
0$
#1105
0!
b1011 +
b111 .
0)
1$
#1110
0$
#1115
b1100 +
b0 .
1$
#1120
0$
#1125
b1101 +
b1 .
1$
#1130
0$
#1135
b1110 +
b10 .
1$
#1140
0$
#1145
b1111 +
b11 .
1$
#1150
0$
#1155
1!
b10000 +
b100 .
1)
1$
#1160
0$
#1165
b10001 +
b101 .
1$
#1170
0$
#1175
b10010 +
b110 .
1$
#1180
0$
#1185
0!
b10011 +
b111 .
0)
1$
#1190
0$
#1195
b10100 +
b0 .
1$
#1200
0$
#1205
b10101 +
b1 .
1$
#1210
0$
#1215
b10110 +
b10 .
1$
#1220
0$
#1225
b10111 +
b11 .
1$
#1230
0$
#1235
1!
b11000 +
b100 .
1)
1$
#1240
0$
#1245
b11001 +
b101 .
1$
#1250
0$
#1255
b11010 +
b110 .
1$
#1260
0$
#1265
0!
b11011 +
b111 .
0)
1$
#1270
0$
#1275
b11100 +
b0 .
1$
#1280
0$
#1285
b11101 +
b1 .
1$
#1290
0$
#1295
b11110 +
b10 .
1$
#1300
0$
#1305
b11111 +
b11 .
1$
#1310
0$
#1315
1!
b100000 +
b100 .
1)
1$
#1320
0$
#1325
b100001 +
b101 .
1$
#1330
0$
#1335
b100010 +
b110 .
1$
#1340
0$
#1345
0!
b100011 +
b111 .
0)
1$
#1350
0$
#1355
b100100 +
b0 .
1$
#1360
0$
#1365
b100101 +
b1 .
1$
#1370
0$
#1375
b100110 +
b10 .
1$
#1380
0$
#1385
b100111 +
b11 .
1$
#1390
0$
#1395
1!
b101000 +
b100 .
1)
1$
#1400
0$
#1405
b101001 +
b101 .
1$
#1410
0$
#1415
b101010 +
b110 .
1$
#1420
0$
#1425
0!
b101011 +
b111 .
0)
1$
#1430
0$
#1435
b101100 +
b0 .
1$
#1440
0$
#1445
b101101 +
b1 .
1$
#1450
0$
#1455
b101110 +
b10 .
1$
#1460
0$
#1465
b101111 +
b11 .
1$
#1470
0$
#1475
1!
b110000 +
b100 .
1)
1$
#1480
0$
#1485
b110001 +
b101 .
1$
#1490
0$
#1495
1(
b0 +
b110 .
1$
#1500
0$
#1505
0!
b1 +
b111 .
0)
1$
#1510
0$
#1515
b10 +
b0 .
1$
#1520
0$
#1525
b11 +
b1 .
1$
#1530
0$
#1535
b100 +
b10 .
1$
#1540
0$
#1545
b101 +
b11 .
1$
#1550
0$
#1555
1!
b110 +
b100 .
1)
1$
#1560
0$
#1565
b111 +
b101 .
1$
#1570
0$
#1575
b1000 +
b110 .
1$
#1580
0$
#1585
0!
b1001 +
b111 .
0)
1$
#1590
0$
#1595
b1010 +
b0 .
1$
#1600
0$
#1605
b1011 +
b1 .
1$
#1610
0$
#1615
b1100 +
b10 .
1$
#1620
0$
#1625
b1101 +
b11 .
1$
#1630
0$
#1635
1!
b1110 +
b100 .
1)
1$
#1640
0$
#1645
b1111 +
b101 .
1$
#1650
0$
#1655
b10000 +
b110 .
1$
#1660
0$
#1665
0!
b10001 +
b111 .
0)
1$
#1670
0$
#1675
b10010 +
b0 .
1$
#1680
0$
#1685
b10011 +
b1 .
1$
#1690
0$
#1695
b10100 +
b10 .
1$
#1700
0$
#1705
b10101 +
b11 .
1$
#1710
0$
#1715
1!
b10110 +
b100 .
1)
1$
#1720
0$
#1725
b10111 +
b101 .
1$
#1730
0$
#1735
b11000 +
b110 .
1$
#1740
0$
#1745
0!
b11001 +
b111 .
0)
1$
#1750
0$
#1755
b11010 +
b0 .
1$
#1760
0$
#1765
b11011 +
b1 .
1$
#1770
0$
#1775
b11100 +
b10 .
1$
#1780
0$
#1785
b11101 +
b11 .
1$
#1790
0$
#1795
1!
b11110 +
b100 .
1)
1$
#1800
0$
#1805
b11111 +
b101 .
1$
#1810
0$
#1815
b100000 +
b110 .
1$
#1820
0$
#1825
0!
b100001 +
b111 .
0)
1$
#1830
0$
#1835
b100010 +
b0 .
1$
#1840
0$
#1845
b100011 +
b1 .
1$
#1850
0$
#1855
b100100 +
b10 .
1$
#1860
0$
#1865
b100101 +
b11 .
1$
#1870
0$
#1875
1!
b100110 +
b100 .
1)
1$
#1880
0$
#1885
b100111 +
b101 .
1$
#1890
0$
#1895
b101000 +
b110 .
1$
#1900
0$
#1905
0!
b101001 +
b111 .
0)
1$
#1910
0$
#1915
b101010 +
b0 .
1$
#1920
0$
#1925
b101011 +
b1 .
1$
#1930
0$
#1935
b101100 +
b10 .
1$
#1940
0$
#1945
b101101 +
b11 .
1$
#1950
0$
#1955
1!
b101110 +
b100 .
1)
1$
#1960
0$
#1965
b101111 +
b101 .
1$
#1970
0$
#1975
b110000 +
b110 .
1$
#1980
0$
#1985
0!
b110001 +
b111 .
0)
1$
#1990
0$
#1995
0(
b0 +
b0 .
1$
#2000
b10 #
b10 *
b10 -
0$
b100 &
b100 '
b100 ,
#2005
b1 +
b1 .
1$
#2010
0$
#2015
b10 +
b10 .
1$
#2020
0$
#2025
b11 +
b11 .
1$
#2030
0$
#2035
1!
b100 +
b100 .
1)
1$
#2040
0$
#2045
b101 +
b101 .
1$
#2050
0$
#2055
b110 +
b110 .
1$
#2060
0$
#2065
0!
b111 +
b111 .
0)
1$
#2070
0$
#2075
b1000 +
b0 .
1$
#2080
0$
#2085
b1001 +
b1 .
1$
#2090
0$
#2095
b1010 +
b10 .
1$
#2100
0$
#2105
b1011 +
b11 .
1$
#2110
0$
#2115
1!
b1100 +
b100 .
1)
1$
#2120
0$
#2125
b1101 +
b101 .
1$
#2130
0$
#2135
b1110 +
b110 .
1$
#2140
0$
#2145
0!
b1111 +
b111 .
0)
1$
#2150
0$
#2155
b10000 +
b0 .
1$
#2160
0$
#2165
b10001 +
b1 .
1$
#2170
0$
#2175
b10010 +
b10 .
1$
#2180
0$
#2185
b10011 +
b11 .
1$
#2190
0$
#2195
1!
b10100 +
b100 .
1)
1$
#2200
0$
#2205
b10101 +
b101 .
1$
#2210
0$
#2215
b10110 +
b110 .
1$
#2220
0$
#2225
0!
b10111 +
b111 .
0)
1$
#2230
0$
#2235
b11000 +
b0 .
1$
#2240
0$
#2245
b11001 +
b1 .
1$
#2250
0$
#2255
b11010 +
b10 .
1$
#2260
0$
#2265
b11011 +
b11 .
1$
#2270
0$
#2275
1!
b11100 +
b100 .
1)
1$
#2280
0$
#2285
b11101 +
b101 .
1$
#2290
0$
#2295
b11110 +
b110 .
1$
#2300
0$
#2305
0!
b11111 +
b111 .
0)
1$
#2310
0$
#2315
b100000 +
b0 .
1$
#2320
0$
#2325
b100001 +
b1 .
1$
#2330
0$
#2335
b100010 +
b10 .
1$
#2340
0$
#2345
b100011 +
b11 .
1$
#2350
0$
#2355
1!
b100100 +
b100 .
1)
1$
#2360
0$
#2365
b100101 +
b101 .
1$
#2370
0$
#2375
b100110 +
b110 .
1$
#2380
0$
#2385
0!
b100111 +
b111 .
0)
1$
#2390
0$
#2395
b101000 +
b0 .
1$
#2400
0$
#2405
b101001 +
b1 .
1$
#2410
0$
#2415
b101010 +
b10 .
1$
#2420
0$
#2425
b101011 +
b11 .
1$
#2430
0$
#2435
1!
b101100 +
b100 .
1)
1$
#2440
0$
#2445
b101101 +
b101 .
1$
#2450
0$
#2455
b101110 +
b110 .
1$
#2460
0$
#2465
0!
b101111 +
b111 .
0)
1$
#2470
0$
#2475
b110000 +
b0 .
1$
#2480
0$
#2485
b110001 +
b1 .
1$
#2490
0$
#2495
1(
b0 +
b10 .
1$
#2500
0$
#2505
b1 +
b11 .
1$
#2510
0$
#2515
1!
b10 +
b100 .
1)
1$
#2520
0$
#2525
b11 +
b101 .
1$
#2530
0$
#2535
b100 +
b110 .
1$
#2540
0$
#2545
0!
b101 +
b111 .
0)
1$
#2550
0$
#2555
b110 +
b0 .
1$
#2560
0$
#2565
b111 +
b1 .
1$
#2570
0$
#2575
b1000 +
b10 .
1$
#2580
0$
#2585
b1001 +
b11 .
1$
#2590
0$
#2595
1!
b1010 +
b100 .
1)
1$
#2600
0$
#2605
b1011 +
b101 .
1$
#2610
0$
#2615
b1100 +
b110 .
1$
#2620
0$
#2625
0!
b1101 +
b111 .
0)
1$
#2630
0$
#2635
b1110 +
b0 .
1$
#2640
0$
#2645
b1111 +
b1 .
1$
#2650
0$
#2655
b10000 +
b10 .
1$
#2660
0$
#2665
b10001 +
b11 .
1$
#2670
0$
#2675
1!
b10010 +
b100 .
1)
1$
#2680
0$
#2685
b10011 +
b101 .
1$
#2690
0$
#2695
b10100 +
b110 .
1$
#2700
0$
#2705
0!
b10101 +
b111 .
0)
1$
#2710
0$
#2715
b10110 +
b0 .
1$
#2720
0$
#2725
b10111 +
b1 .
1$
#2730
0$
#2735
b11000 +
b10 .
1$
#2740
0$
#2745
b11001 +
b11 .
1$
#2750
0$
#2755
1!
b11010 +
b100 .
1)
1$
#2760
0$
#2765
b11011 +
b101 .
1$
#2770
0$
#2775
b11100 +
b110 .
1$
#2780
0$
#2785
0!
b11101 +
b111 .
0)
1$
#2790
0$
#2795
b11110 +
b0 .
1$
#2800
0$
#2805
b11111 +
b1 .
1$
#2810
0$
#2815
b100000 +
b10 .
1$
#2820
0$
#2825
b100001 +
b11 .
1$
#2830
0$
#2835
1!
b100010 +
b100 .
1)
1$
#2840
0$
#2845
b100011 +
b101 .
1$
#2850
0$
#2855
b100100 +
b110 .
1$
#2860
0$
#2865
0!
b100101 +
b111 .
0)
1$
#2870
0$
#2875
b100110 +
b0 .
1$
#2880
0$
#2885
b100111 +
b1 .
1$
#2890
0$
#2895
b101000 +
b10 .
1$
#2900
0$
#2905
b101001 +
b11 .
1$
#2910
0$
#2915
1!
b101010 +
b100 .
1)
1$
#2920
0$
#2925
b101011 +
b101 .
1$
#2930
0$
#2935
b101100 +
b110 .
1$
#2940
0$
#2945
0!
b101101 +
b111 .
0)
1$
#2950
0$
#2955
b101110 +
b0 .
1$
#2960
0$
#2965
b101111 +
b1 .
1$
#2970
0$
#2975
b110000 +
b10 .
1$
#2980
0$
#2985
b110001 +
b11 .
1$
#2990
0$
#2995
1!
0(
b0 +
b100 .
1)
1$
#3000
b11 #
b11 *
b11 -
0$
b1000 &
b1000 '
b1000 ,
#3005
b1 +
b101 .
1$
#3010
0$
#3015
b10 +
b110 .
1$
#3020
0$
#3025
0!
b11 +
b111 .
0)
1$
#3030
0$
#3035
b100 +
b0 .
1$
#3040
0$
#3045
b101 +
b1 .
1$
#3050
0$
#3055
b110 +
b10 .
1$
#3060
0$
#3065
b111 +
b11 .
1$
#3070
0$
#3075
1!
b1000 +
b100 .
1)
1$
#3080
0$
#3085
b1001 +
b101 .
1$
#3090
0$
#3095
b1010 +
b110 .
1$
#3100
0$
#3105
0!
b1011 +
b111 .
0)
1$
#3110
0$
#3115
b1100 +
b0 .
1$
#3120
0$
#3125
b1101 +
b1 .
1$
#3130
0$
#3135
b1110 +
b10 .
1$
#3140
0$
#3145
b1111 +
b11 .
1$
#3150
0$
#3155
1!
b10000 +
b100 .
1)
1$
#3160
0$
#3165
b10001 +
b101 .
1$
#3170
0$
#3175
b10010 +
b110 .
1$
#3180
0$
#3185
0!
b10011 +
b111 .
0)
1$
#3190
0$
#3195
b10100 +
b0 .
1$
#3200
0$
#3205
b10101 +
b1 .
1$
#3210
0$
#3215
b10110 +
b10 .
1$
#3220
0$
#3225
b10111 +
b11 .
1$
#3230
0$
#3235
1!
b11000 +
b100 .
1)
1$
#3240
0$
#3245
b11001 +
b101 .
1$
#3250
0$
#3255
b11010 +
b110 .
1$
#3260
0$
#3265
0!
b11011 +
b111 .
0)
1$
#3270
0$
#3275
b11100 +
b0 .
1$
#3280
0$
#3285
b11101 +
b1 .
1$
#3290
0$
#3295
b11110 +
b10 .
1$
#3300
0$
#3305
b11111 +
b11 .
1$
#3310
0$
#3315
1!
b100000 +
b100 .
1)
1$
#3320
0$
#3325
b100001 +
b101 .
1$
#3330
0$
#3335
b100010 +
b110 .
1$
#3340
0$
#3345
0!
b100011 +
b111 .
0)
1$
#3350
0$
#3355
b100100 +
b0 .
1$
#3360
0$
#3365
b100101 +
b1 .
1$
#3370
0$
#3375
b100110 +
b10 .
1$
#3380
0$
#3385
b100111 +
b11 .
1$
#3390
0$
#3395
1!
b101000 +
b100 .
1)
1$
#3400
0$
#3405
b101001 +
b101 .
1$
#3410
0$
#3415
b101010 +
b110 .
1$
#3420
0$
#3425
0!
b101011 +
b111 .
0)
1$
#3430
0$
#3435
b101100 +
b0 .
1$
#3440
0$
#3445
b101101 +
b1 .
1$
#3450
0$
#3455
b101110 +
b10 .
1$
#3460
0$
#3465
b101111 +
b11 .
1$
#3470
0$
#3475
1!
b110000 +
b100 .
1)
1$
#3480
0$
#3485
b110001 +
b101 .
1$
#3490
0$
#3495
1(
b0 +
b110 .
1$
#3500
0$
#3505
0!
b1 +
b111 .
0)
1$
#3510
0$
#3515
b10 +
b0 .
1$
#3520
0$
#3525
b11 +
b1 .
1$
#3530
0$
#3535
b100 +
b10 .
1$
#3540
0$
#3545
b101 +
b11 .
1$
#3550
0$
#3555
1!
b110 +
b100 .
1)
1$
#3560
0$
#3565
b111 +
b101 .
1$
#3570
0$
#3575
b1000 +
b110 .
1$
#3580
0$
#3585
0!
b1001 +
b111 .
0)
1$
#3590
0$
#3595
b1010 +
b0 .
1$
#3600
0$
#3605
b1011 +
b1 .
1$
#3610
0$
#3615
b1100 +
b10 .
1$
#3620
0$
#3625
b1101 +
b11 .
1$
#3630
0$
#3635
1!
b1110 +
b100 .
1)
1$
#3640
0$
#3645
b1111 +
b101 .
1$
#3650
0$
#3655
b10000 +
b110 .
1$
#3660
0$
#3665
0!
b10001 +
b111 .
0)
1$
#3670
0$
#3675
b10010 +
b0 .
1$
#3680
0$
#3685
b10011 +
b1 .
1$
#3690
0$
#3695
b10100 +
b10 .
1$
#3700
0$
#3705
b10101 +
b11 .
1$
#3710
0$
#3715
1!
b10110 +
b100 .
1)
1$
#3720
0$
#3725
b10111 +
b101 .
1$
#3730
0$
#3735
b11000 +
b110 .
1$
#3740
0$
#3745
0!
b11001 +
b111 .
0)
1$
#3750
0$
#3755
b11010 +
b0 .
1$
#3760
0$
#3765
b11011 +
b1 .
1$
#3770
0$
#3775
b11100 +
b10 .
1$
#3780
0$
#3785
b11101 +
b11 .
1$
#3790
0$
#3795
1!
b11110 +
b100 .
1)
1$
#3800
0$
#3805
b11111 +
b101 .
1$
#3810
0$
#3815
b100000 +
b110 .
1$
#3820
0$
#3825
0!
b100001 +
b111 .
0)
1$
#3830
0$
#3835
b100010 +
b0 .
1$
#3840
0$
#3845
b100011 +
b1 .
1$
#3850
0$
#3855
b100100 +
b10 .
1$
#3860
0$
#3865
b100101 +
b11 .
1$
#3870
0$
#3875
1!
b100110 +
b100 .
1)
1$
#3880
0$
#3885
b100111 +
b101 .
1$
#3890
0$
#3895
b101000 +
b110 .
1$
#3900
0$
#3905
0!
b101001 +
b111 .
0)
1$
#3910
0$
#3915
b101010 +
b0 .
1$
#3920
0$
#3925
b101011 +
b1 .
1$
#3930
0$
#3935
b101100 +
b10 .
1$
#3940
0$
#3945
b101101 +
b11 .
1$
#3950
0$
#3955
1!
b101110 +
b100 .
1)
1$
#3960
0$
#3965
b101111 +
b101 .
1$
#3970
0$
#3975
b110000 +
b110 .
1$
#3980
0$
#3985
0!
b110001 +
b111 .
0)
1$
#3990
0$
#3995
0(
b0 +
b0 .
1$
#4000
b100 #
b100 *
b100 -
0$
b10000 &
b10000 '
b10000 ,
#4005
b1 +
b1 .
1$
#4010
0$
#4015
b10 +
b10 .
1$
#4020
0$
#4025
b11 +
b11 .
1$
#4030
0$
#4035
1!
b100 +
b100 .
1)
1$
#4040
0$
#4045
b101 +
b101 .
1$
#4050
0$
#4055
b110 +
b110 .
1$
#4060
0$
#4065
0!
b111 +
b111 .
0)
1$
#4070
0$
#4075
b1000 +
b0 .
1$
#4080
0$
#4085
b1001 +
b1 .
1$
#4090
0$
#4095
b1010 +
b10 .
1$
#4100
0$
#4105
b1011 +
b11 .
1$
#4110
0$
#4115
1!
b1100 +
b100 .
1)
1$
#4120
0$
#4125
b1101 +
b101 .
1$
#4130
0$
#4135
b1110 +
b110 .
1$
#4140
0$
#4145
0!
b1111 +
b111 .
0)
1$
#4150
0$
#4155
b10000 +
b0 .
1$
#4160
0$
#4165
b10001 +
b1 .
1$
#4170
0$
#4175
b10010 +
b10 .
1$
#4180
0$
#4185
b10011 +
b11 .
1$
#4190
0$
#4195
1!
b10100 +
b100 .
1)
1$
#4200
0$
#4205
b10101 +
b101 .
1$
#4210
0$
#4215
b10110 +
b110 .
1$
#4220
0$
#4225
0!
b10111 +
b111 .
0)
1$
#4230
0$
#4235
b11000 +
b0 .
1$
#4240
0$
#4245
b11001 +
b1 .
1$
#4250
0$
#4255
b11010 +
b10 .
1$
#4260
0$
#4265
b11011 +
b11 .
1$
#4270
0$
#4275
1!
b11100 +
b100 .
1)
1$
#4280
0$
#4285
b11101 +
b101 .
1$
#4290
0$
#4295
b11110 +
b110 .
1$
#4300
0$
#4305
0!
b11111 +
b111 .
0)
1$
#4310
0$
#4315
b100000 +
b0 .
1$
#4320
0$
#4325
b100001 +
b1 .
1$
#4330
0$
#4335
b100010 +
b10 .
1$
#4340
0$
#4345
b100011 +
b11 .
1$
#4350
0$
#4355
1!
b100100 +
b100 .
1)
1$
#4360
0$
#4365
b100101 +
b101 .
1$
#4370
0$
#4375
b100110 +
b110 .
1$
#4380
0$
#4385
0!
b100111 +
b111 .
0)
1$
#4390
0$
#4395
b101000 +
b0 .
1$
#4400
0$
#4405
b101001 +
b1 .
1$
#4410
0$
#4415
b101010 +
b10 .
1$
#4420
0$
#4425
b101011 +
b11 .
1$
#4430
0$
#4435
1!
b101100 +
b100 .
1)
1$
#4440
0$
#4445
b101101 +
b101 .
1$
#4450
0$
#4455
b101110 +
b110 .
1$
#4460
0$
#4465
0!
b101111 +
b111 .
0)
1$
#4470
0$
#4475
b110000 +
b0 .
1$
#4480
0$
#4485
b110001 +
b1 .
1$
#4490
0$
#4495
1(
b0 +
b10 .
1$
#4500
0$
#4505
b1 +
b11 .
1$
#4510
0$
#4515
1!
b10 +
b100 .
1)
1$
#4520
0$
#4525
b11 +
b101 .
1$
#4530
0$
#4535
b100 +
b110 .
1$
#4540
0$
#4545
0!
b101 +
b111 .
0)
1$
#4550
0$
#4555
b110 +
b0 .
1$
#4560
0$
#4565
b111 +
b1 .
1$
#4570
0$
#4575
b1000 +
b10 .
1$
#4580
0$
#4585
b1001 +
b11 .
1$
#4590
0$
#4595
1!
b1010 +
b100 .
1)
1$
#4600
0$
#4605
b1011 +
b101 .
1$
#4610
0$
#4615
b1100 +
b110 .
1$
#4620
0$
#4625
0!
b1101 +
b111 .
0)
1$
#4630
0$
#4635
b1110 +
b0 .
1$
#4640
0$
#4645
b1111 +
b1 .
1$
#4650
0$
#4655
b10000 +
b10 .
1$
#4660
0$
#4665
b10001 +
b11 .
1$
#4670
0$
#4675
1!
b10010 +
b100 .
1)
1$
#4680
0$
#4685
b10011 +
b101 .
1$
#4690
0$
