microondas/delaydebouncing.v
module delaydebouncing(input wire clear, clk,output reg key);
reg [2:0] count;
initial begin
	count<=0;
	key<=0;
end
always @(posedge clk or posedge clear) begin
	if (clear) begin
		count<=0;
		key<=0;
	end
	case(count)
		3'b011:begin key<=1; count<=count+1; end// considerando o 011(2)==3(10) porque a mudança só acontece após o pulso de clock
		3'b110:begin key<=0; count<=count+1; end// mesma consideração aqui
		3'b111:count<=0;
		default:count<=count+1;
	endcase
end
endmodule

entrada timer e controle/delaydebouncing/delaydebouncing_tb.v
`timescale 1ns/1ns
module delaydebouncing_tb();
reg clk_tb=0,clear_tb=0;
wire key_tb;
integer i;
delaydebouncing DUT (.clk(clk_tb),.clear(clear_tb),.key(key_tb));
initial begin
	$dumpfile("delaydebouncing_tb.vcd");
	$dumpvars(0,delaydebouncing_tb);
	repeat(500)
		#5 clk_tb=~clk_tb;
end

initial begin// teste do clear
	#302;
	clear_tb=1;
	#5;
	clear_tb=0;
end

endmodule

entrada timer e controle/delaydebouncing/delaydebouncing_tb.vcd
$date
	Mon Apr 26 10:02:14 2021
$end
$version
	Icarus Verilog
$end
$timescale
	1ns
$end
$scope module delaydebouncing_tb $end
$var wire 1 ! key_tb $end
$var reg 1 " clear_tb $end
$var reg 1 # clk_tb $end
$scope module DUT $end
$var wire 1 " clear $end
$var wire 1 # clk $end
$var reg 3 $ count [2:0] $end
$var reg 1 ! key $end
$upscope $end
$upscope $end
$enddefinitions $end
#0
$dumpvars
b0 $
0#
0"
0!
$end
#5
b1 $
1#
#10
0#
#15
b10 $
1#
#20
0#
#25
b11 $
1#
#30
0#
#35
b100 $
1!
1#
#40
0#
#45
b101 $
1#
#50
0#
#55
b110 $
1#
#60
0#
#65
b111 $
0!
1#
#70
0#
#75
b0 $
1#
#80
0#
#85
b1 $
1#
#90
0#
#95
b10 $
1#
#100
0#
#105
b11 $
1#
#110
0#
#115
b100 $
1!
1#
#120
0#
#125
b101 $
1#
#130
0#
#135
b110 $
1#
#140
0#
#145
b111 $
0!
1#
#150
0#
#155
b0 $
1#
#160
0#
#165
b1 $
1#
#170
0#
#175
b10 $
1#
#180
0#
#185
b11 $
1#
#190
0#
#195
b100 $
1!
1#
#200
0#
#205
b101 $
1#
#210
0#
#215
b110 $
1#
#220
0#
#225
b111 $
0!
1#
#230
0#
#235
b0 $
1#
#240
0#
#245
b1 $
1#
#250
0#
#255
b10 $
1#
#260
0#
#265
b11 $
1#
#270
0#
#275
b100 $
1!
1#
#280
0#
#285
b101 $
1#
#290
0#
#295
b110 $
1#
#300
0#
#302
0!
b111 $
1"
#305
b0 $
1#
#307
0"
#310
0#
#315
b1 $
1#
#320
0#
#325
b10 $
1#
#330
0#
#335
b11 $
1#
#340
0#
#345
b100 $
1!
1#
#350
0#
#355
b101 $
1#
#360
0#
#365
b110 $
1#
#370
0#
#375
b111 $
0!
1#
#380
0#
#385
b0 $
1#
#390
0#
#395
b1 $
1#
#400
0#
#405
b10 $
1#
#410
0#
#415
b11 $
1#
#420
0#
#425
b100 $
1!
1#
#430
0#
#435
b101 $
1#
#440
0#
#445
b110 $
1#
#450
0#
#455
b111 $
0!
1#
#460
0#
#465
b0 $
1#
#470
0#
#475
b1 $
1#
#480
0#
#485
b10 $
1#
#490
0#
#495
b11 $
1#
#500
0#
#505
b100 $
1!
1#
#510
0#
#515
b101 $
1#
#520
0#
#525
b110 $
1#
#530
0#
#535
b111 $
0!
1#
#540
0#
#545
b0 $
1#
#550
0#
#555
b1 $
1#
#560
0#
#565
b10 $
1#
#570
0#
#575
b11 $
1#
#580
0#
#585
b100 $
1!
1#
#590
0#
#595
b101 $
1#
#600
0#
#605
b110 $
1#
#610
0#
#615
b111 $
0!
1#
#620
0#
#625
b0 $
1#
#630
0#
#635
b1 $
1#
#640
0#
#645
b10 $
1#
#650
0#
#655
b11 $
1#
#660
0#
#665
b100 $
1!
1#
#670
0#
#675
b101 $
1#
#680
0#
#685
b110 $
1#
#690
0#
#695
b111 $
0!
1#
#700
0#
#705
b0 $
1#
#710
0#
#715
b1 $
1#
#720
0#
#725
b10 $
1#
#730
0#
#735
b11 $
1#
#740
0#
#745
b100 $
1!
1#
#750
0#
#755
b101 $
1#
#760
0#
#765
b110 $
1#
#770
0#
#775
b111 $
0!
1#
#780
0#
#785
b0 $
1#
#790
0#
#795
b1 $
1#
#800
0#
#805
b10 $
1#
#810
0#
#815
b11 $
1#
#820
0#
#825
b100 $
1!
1#
#830
0#
#835
b101 $
1#
#840
0#
#845
b110 $
1#
#850
0#
#855
b111 $
0!
1#
#860
0#
#865
b0 $
1#
#870
0#
#875
b1 $
1#
#880
0#
#885
b10 $
1#
#890
0#
#895
b11 $
1#
#900
0#
#905
b100 $
1!
1#
#910
0#
#915
b101 $
1#
#920
0#
#925
b110 $
1#
#930
0#
#935
b111 $
0!
1#
#940
0#
#945
b0 $
1#
#950
0#
#955
b1 $
1#
#960
0#
#965
b10 $
1#
#970
0#
#975
b11 $
1#
#980
0#
#985
b100 $
1!
1#
#990
0#
#995
b101 $
1#
#1000
0#
#1005
b110 $
1#
#1010
0#
#1015
b111 $
0!
1#
#1020
0#
#1025
b0 $
1#
#1030
0#
#1035
b1 $
1#
#1040
0#
#1045
b10 $
1#
#1050
0#
#1055
b11 $
1#
#1060
0#
#1065
b100 $
1!
1#
#1070
0#
#1075
b101 $
1#
#1080
0#
#1085
b110 $
1#
#1090
0#
#1095
b111 $
0!
1#
#1100
0#
#1105
b0 $
1#
#1110
0#
#1115
b1 $
1#
#1120
0#
#1125
b10 $
1#
#1130
0#
#1135
b11 $
1#
#1140
0#
#1145
b100 $
1!
1#
#1150
0#
#1155
b101 $
1#
#1160
0#
#1165
b110 $
1#
#1170
0#
#1175
b111 $
0!
1#
#1180
0#
#1185
b0 $
1#
#1190
0#
#1195
b1 $
1#
#1200
0#
#1205
b10 $
1#
#1210
0#
#1215
b11 $
1#
#1220
0#
#1225
b100 $
1!
1#
#1230
0#
#1235
b101 $
1#
#1240
0#
#1245
b110 $
1#
#1250
0#
#1255
b111 $
0!
1#
#1260
0#
#1265
b0 $
1#
#1270
0#
#1275
b1 $
1#
#1280
0#
#1285
b10 $
1#
#1290
0#
#1295
b11 $
1#
#1300
0#
#1305
b100 $
1!
1#
#1310
0#
#1315
b101 $
1#
#1320
0#
#1325
b110 $
1#
#1330
0#
#1335
b111 $
0!
1#
#1340
0#
#1345
b0 $
1#
#1350
0#
#1355
b1 $
1#
#1360
0#
#1365
b10 $
1#
#1370
0#
#1375
b11 $
1#
#1380
0#
#1385
b100 $
1!
1#
#1390
0#
#1395
b101 $
1#
#1400
0#
#1405
b110 $
1#
#1410
0#
#1415
b111 $
0!
1#
#1420
0#
#1425
b0 $
1#
#1430
0#
#1435
b1 $
1#
#1440
0#
#1445
b10 $
1#
#1450
0#
#1455
b11 $
1#
#1460
0#
#1465
b100 $
1!
1#
#1470
0#
#1475
b101 $
1#
#1480
0#
#1485
b110 $
1#
#1490
0#
#1495
b111 $
0!
1#
#1500
0#
#1505
b0 $
1#
#1510
0#
#1515
b1 $
1#
#1520
0#
#1525
b10 $
1#
#1530
0#
#1535
b11 $
1#
#1540
0#
#1545
b100 $
1!
1#
#1550
0#
#1555
b101 $
1#
#1560
0#
#1565
b110 $
1#
#1570
0#
#1575
b111 $
0!
1#
#1580
0#
#1585
b0 $
1#
#1590
0#
#1595
b1 $
1#
#1600
0#
#1605
b10 $
1#
#1610
0#
#1615
b11 $
1#
#1620
0#
#1625
b100 $
1!
1#
#1630
0#
#1635
b101 $
1#
#1640
0#
#1645
b110 $
1#
#1650
0#
#1655
b111 $
0!
1#
#1660
0#
#1665
b0 $
1#
#1670
0#
#1675
b1 $
1#
#1680
0#
#1685
b10 $
1#
#1690
0#
#1695
b11 $
1#
#1700
0#
#1705
b100 $
1!
1#
#1710
0#
#1715
b101 $
1#
#1720
0#
#1725
b110 $
1#
#1730
0#
#1735
b111 $
0!
1#
#1740
0#
#1745
b0 $
1#
#1750
0#
#1755
b1 $
1#
#1760
0#
#1765
b10 $
1#
#1770
0#
#1775
b11 $
1#
#1780
0#
#1785
b100 $
1!
1#
#1790
0#
#1795
b101 $
1#
#1800
0#
#1805
b110 $
1#
#1810
0#
#1815
b111 $
0!
1#
#1820
0#
#1825
b0 $
1#
#1830
0#
#1835
b1 $
1#
#1840
0#
#1845
b10 $
1#
#1850
0#
#1855
b11 $
1#
#1860
0#
#1865
b100 $
1!
1#
#1870
0#
#1875
b101 $
1#
#1880
0#
#1885
b110 $
1#
#1890
0#
#1895
b111 $
0!
1#
#1900
0#
#1905
b0 $
1#
#1910
0#
#1915
b1 $
1#
#1920
0#
#1925
b10 $
1#
#1930
0#
#1935
b11 $
1#
#1940
0#
#1945
b100 $
1!
1#
#1950
0#
#1955
b101 $
1#
#1960
0#
#1965
b110 $
1#
#1970
0#
#1975
b111 $
0!
1#
#1980
0#
#1985
b0 $
1#
#1990
0#
#1995
b1 $
1#
#2000
0#
#2005
b10 $
1#
#2010
0#
#2015
b11 $
1#
#2020
0#
#2025
b100 $
1!
1#
#2030
0#
#2035
b101 $
1#
#2040
0#
#2045
b110 $
1#
#2050
0#
#2055
b111 $
0!
1#
#2060
0#
#2065
b0 $
1#
#2070
0#
#2075
b1 $
1#
#2080
0#
#2085
b10 $
1#
#2090
0#
#2095
b11 $
1#
#2100
0#
#2105
b100 $
1!
1#
#2110
0#
#2115
b101 $
1#
#2120
0#
#2125
b110 $
1#
#2130
0#
#2135
b111 $
0!
1#
#2140
0#
#2145
b0 $
1#
#2150
0#
#2155
b1 $
1#
#2160
0#
#2165
b10 $
1#
#2170
0#
#2175
b11 $
1#
#2180
0#
#2185
b100 $
1!
1#
#2190
0#
#2195
b101 $
1#
#2200
0#
#2205
b110 $
1#
#2210
0#
#2215
b111 $
0!
1#
#2220
0#
#2225
b0 $
1#
#2230
0#
#2235
b1 $
1#
#2240
0#
#2245
b10 $
1#
#2250
0#
#2255
b11 $
1#
#2260
0#
#2265
b100 $
1!
1#
#2270
0#
#2275
b101 $
1#
#2280
0#
#2285
b110 $
1#
#2290
0#
#2295
b111 $
0!
1#
#2300
0#
#2305
b0 $
1#
#2310
0#
#2315
b1 $
1#
#2320
0#
#2325
b10 $
1#
#2330
0#
#2335
b11 $
1#
#2340
0#
#2345
b100 $
1!
1#
#2350
0#
#2355
b101 $
1#
#2360
0#
#2365
b110 $
1#
#2370
0#
#2375
b111 $
0!
1#
#2380
0#
#2385
b0 $
1#
#2390
0#
#2395
b1 $
1#
#2400
0#
#2405
b10 $
1#
#2410
0#
#2415
b11 $
1#
#2420
0#
#2425
b100 $
1!
1#
#2430
0#
#2435
b101 $
1#
#2440
0#
#2445
b110 $
1#
#2450
0#
#2455
b111 $
0!
1#
#2460
0#
#2465
b0 $
1#
#2470
0#
#2475
b1 $
1#
#2480
0#
#2485
b10 $
1#
#2490
0#
#2495
b11 $
1#
