controle magnetron/mag_on.v
module mag_on(
  input wire STARTN, STOPN, CLEARN, DOOR, timer_done,
  output wire mag
);
  
  wire nq, SET, RESET;
  
  assign RESET = STARTN | !STOPN | !CLEARN | !DOOR | timer_done;// todos os outros casos sem ser o da ativação
  assign SET = !STARTN & STOPN & CLEARN & DOOR & !timer_done; // funciona somente com o start==0, stop==1, clear==1, door(door_closed)==1 e timer_done==0. Isso considerando que algumas portas funcionam somente ativas em nível BAIXO
  
  //descrição comportamental do Latch SR
  nor g1(mag, RESET, nq);
  nor g2(nq, SET, mag);
endmodule

controle magnetron/mag_on_testbench.v
`timescale 1ms/1ms
module mag_on_testbench();
  reg startn_test, stopn_test,  clearn_test, doorn_test, timerDone_test;
  wire mag_test;
  integer i;
  mag_on ut(startn_test, stopn_test, clearn_test, doorn_test, timerDone_test, mag_test);
  //como a variação são de 5 bits, 2^5=32, então:
  initial 
        begin
        $dumpfile("mag_on_testbench.vcd");
        $dumpvars(0,mag_on_testbench);
        i=0;
          for(i=0;i<32;i=i+1)//verificando todas as possibilidades para garantir que o magnetron funcione com a combinação correta
          #1 {startn_test,stopn_test,clearn_test,doorn_test,timerDone_test}=i;

        end
endmodule

controle magnetron/mag_on_testbench.vcd
$date
	Mon Apr 26 11:29:44 2021
$end
$version
	Icarus Verilog
$end
$timescale
	1ms
$end
$scope module mag_on_testbench $end
$var wire 1 ! mag_test $end
$var reg 1 " clearn_test $end
$var reg 1 # doorn_test $end
$var reg 1 $ startn_test $end
$var reg 1 % stopn_test $end
$var reg 1 & timerDone_test $end
$var integer 32 ' i [31:0] $end
$scope module ut $end
$var wire 1 " CLEARN $end
$var wire 1 # DOOR $end
$var wire 1 ( RESET $end
$var wire 1 ) SET $end
$var wire 1 $ STARTN $end
$var wire 1 % STOPN $end
$var wire 1 ! mag $end
$var wire 1 * nq $end
$var wire 1 & timer_done $end
$upscope $end
$upscope $end
$enddefinitions $end
#0
$dumpvars
x*
x)
x(
b0 '
x&
x%
x$
x#
x"
x!
$end
#1
1*
0!
0)
1(
b1 '
0$
0%
0"
0#
0&
#2
b10 '
1&
#3
b11 '
1#
0&
#4
b100 '
1&
#5
b101 '
1"
0#
0&
#6
b110 '
1&
#7
b111 '
1#
0&
#8
b1000 '
1&
#9
b1001 '
1%
0"
0#
0&
#10
b1010 '
1&
#11
b1011 '
1#
0&
#12
b1100 '
1&
#13
b1101 '
1"
0#
0&
#14
b1110 '
1&
#15
1!
0*
1)
0(
b1111 '
1#
0&
#16
1*
0!
1(
0)
b10000 '
1&
#17
0!
1*
1(
0)
b10001 '
1$
0%
0"
0#
0&
#18
b10010 '
1&
#19
b10011 '
1#
0&
#20
b10100 '
1&
#21
b10101 '
1"
0#
0&
#22
b10110 '
1&
#23
b10111 '
1#
0&
#24
b11000 '
1&
#25
b11001 '
1%
0"
0#
0&
#26
b11010 '
1&
#27
b11011 '
1#
0&
#28
b11100 '
1&
#29
b11101 '
1"
0#
0&
#30
b11110 '
1&
#31
b11111 '
1#
0&
#32
b100000 '
1&
