decodificador 7 segmentos/bcd_7segmentos.v
module bcd_7segmentos(input wire [3:0]mins,sec_tens,sec_ones, output reg [6:0]min_segs,sec_tens_segs,sec_ones_segs);
always@* begin
	case(mins)			  
		4'b0000: min_segs = 7'b0000001;
        4'b0001: min_segs = 7'b1001111;
        4'b0010: min_segs = 7'b0010010;
        4'b0011: min_segs = 7'b0000110;
        4'b0100: min_segs = 7'b1001100;
        4'b0101: min_segs = 7'b0100100;
        4'b0110: min_segs = 7'b0100000;
        4'b0111: min_segs = 7'b0001111;
        4'b1000: min_segs = 7'b0000000;
        4'b1001: min_segs = 7'b0001100;
		default: min_segs = 7'b1111111;//considerando o display de 7 segmentos como ânodo comum
	endcase
	case(sec_tens)			  
		4'b0000: sec_tens_segs = 7'b0000001;
        4'b0001: sec_tens_segs = 7'b1001111;
        4'b0010: sec_tens_segs = 7'b0010010;
        4'b0011: sec_tens_segs = 7'b0000110;
        4'b0100: sec_tens_segs = 7'b1001100;
        4'b0101: sec_tens_segs = 7'b0100100;
        4'b0110: sec_tens_segs = 7'b0100000;
        4'b0111: sec_tens_segs = 7'b0001111;
        4'b1000: sec_tens_segs = 7'b0000000;
        4'b1001: sec_tens_segs = 7'b0001100;
		default: sec_tens_segs = 7'b1111111;
	endcase
	case(sec_ones)			  
		4'b0000: sec_ones_segs = 7'b0000001;
        4'b0001: sec_ones_segs = 7'b1001111;
        4'b0010: sec_ones_segs = 7'b0010010;
        4'b0011: sec_ones_segs = 7'b0000110;
        4'b0100: sec_ones_segs = 7'b1001100;
        4'b0101: sec_ones_segs = 7'b0100100;
        4'b0110: sec_ones_segs = 7'b0100000;
        4'b0111: sec_ones_segs = 7'b0001111;
        4'b1000: sec_ones_segs = 7'b0000000;
        4'b1001: sec_ones_segs = 7'b0001100;
		default: sec_ones_segs = 7'b1111111;
	endcase
end
endmodule

decodificador 7 segmentos/bcd_7segmentos_tb.v
`timescale 1ns/1ns
module bcd_7segmentos_tb();
reg [3:0]mins_tb,sec_tens_tb,sec_ones_tb;
wire [6:0]min_segs_tb,sec_tens_segs_tb,sec_ones_segs_tb;
integer i;
bcd_7segmentos DUT(.mins(mins_tb),.sec_tens(sec_tens_tb),.sec_ones(sec_ones_tb),.min_segs(min_segs_tb),.sec_ones_segs(sec_ones_segs_tb),.sec_tens_segs(sec_tens_segs_tb));
initial begin
    $dumpfile("bcd_7segmentos_tb.vcd");
    $dumpvars(0,bcd_7segmentos_tb);
    i=0;
    for(i=0;i<4096;i=i+1)// testando todas as possibilidades
    #10 {mins_tb,sec_tens_tb,sec_ones_tb}=i;

end

endmodule

decodificador 7 segmentos/bcd_7segmentos_tb.vcd
$date
	Thu Apr 29 18:23:28 2021
$end
$version
	Icarus Verilog
$end
$timescale
	1ns
$end
$scope module bcd_7segmentos_tb $end
$var wire 7 ! sec_tens_segs_tb [6:0] $end
$var wire 7 " sec_ones_segs_tb [6:0] $end
$var wire 7 # min_segs_tb [6:0] $end
$var reg 4 $ mins_tb [3:0] $end
$var reg 4 % sec_ones_tb [3:0] $end
$var reg 4 & sec_tens_tb [3:0] $end
$var integer 32 ' i [31:0] $end
$scope module DUT $end
$var wire 4 ( mins [3:0] $end
$var wire 4 ) sec_ones [3:0] $end
$var wire 4 * sec_tens [3:0] $end
$var reg 7 + min_segs [6:0] $end
$var reg 7 , sec_ones_segs [6:0] $end
$var reg 7 - sec_tens_segs [6:0] $end
$upscope $end
$upscope $end
$enddefinitions $end
#0
$dumpvars
bx -
bx ,
bx +
bx *
bx )
bx (
b0 '
bx &
bx %
bx $
bx #
bx "
bx !
$end
#10
b1 "
b1 ,
b1 !
b1 -
b1 #
b1 +
b1 '
b0 $
b0 (
b0 &
b0 *
b0 %
b0 )
#20
b1001111 "
b1001111 ,
b10 '
b1 %
b1 )
#30
b10010 "
b10010 ,
b11 '
b10 %
b10 )
#40
b110 "
b110 ,
b100 '
b11 %
b11 )
#50
b1001100 "
b1001100 ,
b101 '
b100 %
b100 )
#60
b100100 "
b100100 ,
b110 '
b101 %
b101 )
#70
b100000 "
b100000 ,
b111 '
b110 %
b110 )
#80
b1111 "
b1111 ,
b1000 '
b111 %
b111 )
#90
b0 "
b0 ,
b1001 '
b1000 %
b1000 )
#100
b1100 "
b1100 ,
b1010 '
b1001 %
b1001 )
#110
b1111111 "
b1111111 ,
b1011 '
b1010 %
b1010 )
#120
b1100 '
b1011 %
b1011 )
#130
b1101 '
b1100 %
b1100 )
#140
b1110 '
b1101 %
b1101 )
#150
b1111 '
b1110 %
b1110 )
#160
b10000 '
b1111 %
b1111 )
#170
b1 "
b1 ,
b1001111 !
b1001111 -
b10001 '
b1 &
b1 *
b0 %
b0 )
#180
b1001111 "
b1001111 ,
b10010 '
b1 %
b1 )
#190
b10010 "
b10010 ,
b10011 '
b10 %
b10 )
#200
b110 "
b110 ,
b10100 '
b11 %
b11 )
#210
b1001100 "
b1001100 ,
b10101 '
b100 %
b100 )
#220
b100100 "
b100100 ,
b10110 '
b101 %
b101 )
#230
b100000 "
b100000 ,
b10111 '
b110 %
b110 )
#240
b1111 "
b1111 ,
b11000 '
b111 %
b111 )
#250
b0 "
b0 ,
b11001 '
b1000 %
b1000 )
#260
b1100 "
b1100 ,
b11010 '
b1001 %
b1001 )
#270
b1111111 "
b1111111 ,
b11011 '
b1010 %
b1010 )
#280
b11100 '
b1011 %
b1011 )
#290
b11101 '
b1100 %
b1100 )
#300
b11110 '
b1101 %
b1101 )
#310
b11111 '
b1110 %
b1110 )
#320
b100000 '
b1111 %
b1111 )
#330
b1 "
b1 ,
b10010 !
b10010 -
b100001 '
b10 &
b10 *
b0 %
b0 )
#340
b1001111 "
b1001111 ,
b100010 '
b1 %
b1 )
#350
b10010 "
b10010 ,
b100011 '
b10 %
b10 )
#360
b110 "
b110 ,
b100100 '
b11 %
b11 )
#370
b1001100 "
b1001100 ,
b100101 '
b100 %
b100 )
#380
b100100 "
b100100 ,
b100110 '
b101 %
b101 )
#390
b100000 "
b100000 ,
b100111 '
b110 %
b110 )
#400
b1111 "
b1111 ,
b101000 '
b111 %
b111 )
#410
b0 "
b0 ,
b101001 '
b1000 %
b1000 )
#420
b1100 "
b1100 ,
b101010 '
b1001 %
b1001 )
#430
b1111111 "
b1111111 ,
b101011 '
b1010 %
b1010 )
#440
b101100 '
b1011 %
b1011 )
#450
b101101 '
b1100 %
b1100 )
#460
b101110 '
b1101 %
b1101 )
#470
b101111 '
b1110 %
b1110 )
#480
b110000 '
b1111 %
b1111 )
#490
b1 "
b1 ,
b110 !
b110 -
b110001 '
b11 &
b11 *
b0 %
b0 )
#500
b1001111 "
b1001111 ,
b110010 '
b1 %
b1 )
#510
b10010 "
b10010 ,
b110011 '
b10 %
b10 )
#520
b110 "
b110 ,
b110100 '
b11 %
b11 )
#530
b1001100 "
b1001100 ,
b110101 '
b100 %
b100 )
#540
b100100 "
b100100 ,
b110110 '
b101 %
b101 )
#550
b100000 "
b100000 ,
b110111 '
b110 %
b110 )
#560
b1111 "
b1111 ,
b111000 '
b111 %
b111 )
#570
b0 "
b0 ,
b111001 '
b1000 %
b1000 )
#580
b1100 "
b1100 ,
b111010 '
b1001 %
b1001 )
#590
b1111111 "
b1111111 ,
b111011 '
b1010 %
b1010 )
#600
b111100 '
b1011 %
b1011 )
#610
b111101 '
b1100 %
b1100 )
#620
b111110 '
b1101 %
b1101 )
#630
b111111 '
b1110 %
b1110 )
#640
b1000000 '
b1111 %
b1111 )
#650
b1 "
b1 ,
b1001100 !
b1001100 -
b1000001 '
b100 &
b100 *
b0 %
b0 )
#660
b1001111 "
b1001111 ,
b1000010 '
b1 %
b1 )
#670
b10010 "
b10010 ,
b1000011 '
b10 %
b10 )
#680
b110 "
b110 ,
b1000100 '
b11 %
b11 )
#690
b1001100 "
b1001100 ,
b1000101 '
b100 %
b100 )
#700
b100100 "
b100100 ,
b1000110 '
b101 %
b101 )
#710
b100000 "
b100000 ,
b1000111 '
b110 %
b110 )
#720
b1111 "
b1111 ,
b1001000 '
b111 %
b111 )
#730
b0 "
b0 ,
b1001001 '
b1000 %
b1000 )
#740
b1100 "
b1100 ,
b1001010 '
b1001 %
b1001 )
#750
b1111111 "
b1111111 ,
b1001011 '
b1010 %
b1010 )
#760
b1001100 '
b1011 %
b1011 )
#770
b1001101 '
b1100 %
b1100 )
#780
b1001110 '
b1101 %
b1101 )
#790
b1001111 '
b1110 %
b1110 )
#800
b1010000 '
b1111 %
b1111 )
#810
b1 "
b1 ,
b100100 !
b100100 -
b1010001 '
b101 &
b101 *
b0 %
b0 )
#820
b1001111 "
b1001111 ,
b1010010 '
b1 %
b1 )
#830
b10010 "
b10010 ,
b1010011 '
b10 %
b10 )
#840
b110 "
b110 ,
b1010100 '
b11 %
b11 )
#850
b1001100 "
b1001100 ,
b1010101 '
b100 %
b100 )
#860
b100100 "
b100100 ,
b1010110 '
b101 %
b101 )
#870
b100000 "
b100000 ,
b1010111 '
b110 %
b110 )
#880
b1111 "
b1111 ,
b1011000 '
b111 %
b111 )
#890
b0 "
b0 ,
b1011001 '
b1000 %
b1000 )
#900
b1100 "
b1100 ,
b1011010 '
b1001 %
b1001 )
#910
b1111111 "
b1111111 ,
b1011011 '
b1010 %
b1010 )
#920
b1011100 '
b1011 %
b1011 )
#930
b1011101 '
b1100 %
b1100 )
#940
b1011110 '
b1101 %
b1101 )
#950
b1011111 '
b1110 %
b1110 )
#960
b1100000 '
b1111 %
b1111 )
#970
b1 "
b1 ,
b100000 !
b100000 -
b1100001 '
b110 &
b110 *
b0 %
b0 )
#980
b1001111 "
b1001111 ,
b1100010 '
b1 %
b1 )
#990
b10010 "
b10010 ,
b1100011 '
b10 %
b10 )
#1000
b110 "
b110 ,
b1100100 '
b11 %
b11 )
#1010
b1001100 "
b1001100 ,
b1100101 '
b100 %
b100 )
#1020
b100100 "
b100100 ,
b1100110 '
b101 %
b101 )
#1030
b100000 "
b100000 ,
b1100111 '
b110 %
b110 )
#1040
b1111 "
b1111 ,
b1101000 '
b111 %
b111 )
#1050
b0 "
b0 ,
b1101001 '
b1000 %
b1000 )
#1060
b1100 "
b1100 ,
b1101010 '
b1001 %
b1001 )
#1070
b1111111 "
b1111111 ,
b1101011 '
b1010 %
b1010 )
#1080
b1101100 '
b1011 %
b1011 )
#1090
b1101101 '
b1100 %
b1100 )
#1100
b1101110 '
b1101 %
b1101 )
#1110
b1101111 '
b1110 %
b1110 )
#1120
b1110000 '
b1111 %
b1111 )
#1130
b1 "
b1 ,
b1111 !
b1111 -
b1110001 '
b111 &
b111 *
b0 %
b0 )
#1140
b1001111 "
b1001111 ,
b1110010 '
b1 %
b1 )
#1150
b10010 "
b10010 ,
b1110011 '
b10 %
b10 )
#1160
b110 "
b110 ,
b1110100 '
b11 %
b11 )
#1170
b1001100 "
b1001100 ,
b1110101 '
b100 %
b100 )
#1180
b100100 "
b100100 ,
b1110110 '
b101 %
b101 )
#1190
b100000 "
b100000 ,
b1110111 '
b110 %
b110 )
#1200
b1111 "
b1111 ,
b1111000 '
b111 %
b111 )
#1210
b0 "
b0 ,
b1111001 '
b1000 %
b1000 )
#1220
b1100 "
b1100 ,
b1111010 '
b1001 %
b1001 )
#1230
b1111111 "
b1111111 ,
b1111011 '
b1010 %
b1010 )
#1240
b1111100 '
b1011 %
b1011 )
#1250
b1111101 '
b1100 %
b1100 )
#1260
b1111110 '
b1101 %
b1101 )
#1270
b1111111 '
b1110 %
b1110 )
#1280
b10000000 '
b1111 %
b1111 )
#1290
b1 "
b1 ,
b0 !
b0 -
b10000001 '
b1000 &
b1000 *
b0 %
b0 )
#1300
b1001111 "
b1001111 ,
b10000010 '
b1 %
b1 )
#1310
b10010 "
b10010 ,
b10000011 '
b10 %
b10 )
#1320
b110 "
b110 ,
b10000100 '
b11 %
b11 )
#1330
b1001100 "
b1001100 ,
b10000101 '
b100 %
b100 )
#1340
b100100 "
b100100 ,
b10000110 '
b101 %
b101 )
#1350
b100000 "
b100000 ,
b10000111 '
b110 %
b110 )
#1360
b1111 "
b1111 ,
b10001000 '
b111 %
b111 )
#1370
b0 "
b0 ,
b10001001 '
b1000 %
b1000 )
#1380
b1100 "
b1100 ,
b10001010 '
b1001 %
b1001 )
#1390
b1111111 "
b1111111 ,
b10001011 '
b1010 %
b1010 )
#1400
b10001100 '
b1011 %
b1011 )
#1410
b10001101 '
b1100 %
b1100 )
#1420
b10001110 '
b1101 %
b1101 )
#1430
b10001111 '
b1110 %
b1110 )
#1440
b10010000 '
b1111 %
b1111 )
#1450
b1 "
b1 ,
b1100 !
b1100 -
b10010001 '
b1001 &
b1001 *
b0 %
b0 )
#1460
b1001111 "
b1001111 ,
b10010010 '
b1 %
b1 )
#1470
b10010 "
b10010 ,
b10010011 '
b10 %
b10 )
#1480
b110 "
b110 ,
b10010100 '
b11 %
b11 )
#1490
b1001100 "
b1001100 ,
b10010101 '
b100 %
b100 )
#1500
b100100 "
b100100 ,
b10010110 '
b101 %
b101 )
#1510
b100000 "
b100000 ,
b10010111 '
b110 %
b110 )
#1520
b1111 "
b1111 ,
b10011000 '
b111 %
b111 )
#1530
b0 "
b0 ,
b10011001 '
b1000 %
b1000 )
#1540
b1100 "
b1100 ,
b10011010 '
b1001 %
b1001 )
#1550
b1111111 "
b1111111 ,
b10011011 '
b1010 %
b1010 )
#1560
b10011100 '
b1011 %
b1011 )
#1570
b10011101 '
b1100 %
b1100 )
#1580
b10011110 '
b1101 %
b1101 )
#1590
b10011111 '
b1110 %
b1110 )
#1600
b10100000 '
b1111 %
b1111 )
#1610
b1 "
b1 ,
b1111111 !
b1111111 -
b10100001 '
b1010 &
b1010 *
b0 %
b0 )
#1620
b1001111 "
b1001111 ,
b10100010 '
b1 %
b1 )
#1630
b10010 "
b10010 ,
b10100011 '
b10 %
b10 )
#1640
b110 "
b110 ,
b10100100 '
b11 %
b11 )
#1650
b1001100 "
b1001100 ,
b10100101 '
b100 %
b100 )
#1660
b100100 "
b100100 ,
b10100110 '
b101 %
b101 )
#1670
b100000 "
b100000 ,
b10100111 '
b110 %
b110 )
#1680
b1111 "
b1111 ,
b10101000 '
b111 %
b111 )
#1690
b0 "
b0 ,
b10101001 '
b1000 %
b1000 )
#1700
b1100 "
b1100 ,
b10101010 '
b1001 %
b1001 )
#1710
b1111111 "
b1111111 ,
b10101011 '
b1010 %
b1010 )
#1720
b10101100 '
b1011 %
b1011 )
#1730
b10101101 '
b1100 %
b1100 )
#1740
b10101110 '
b1101 %
b1101 )
#1750
b10101111 '
b1110 %
b1110 )
#1760
b10110000 '
b1111 %
b1111 )
#1770
b1 "
b1 ,
b10110001 '
b1011 &
b1011 *
b0 %
b0 )
#1780
b1001111 "
b1001111 ,
b10110010 '
b1 %
b1 )
#1790
b10010 "
b10010 ,
b10110011 '
b10 %
b10 )
#1800
b110 "
b110 ,
b10110100 '
b11 %
b11 )
#1810
b1001100 "
b1001100 ,
b10110101 '
b100 %
b100 )
#1820
b100100 "
b100100 ,
b10110110 '
b101 %
b101 )
#1830
b100000 "
b100000 ,
b10110111 '
b110 %
b110 )
#1840
b1111 "
b1111 ,
b10111000 '
b111 %
b111 )
#1850
b0 "
b0 ,
b10111001 '
b1000 %
b1000 )
#1860
b1100 "
b1100 ,
b10111010 '
b1001 %
b1001 )
#1870
b1111111 "
b1111111 ,
b10111011 '
b1010 %
b1010 )
#1880
b10111100 '
b1011 %
b1011 )
#1890
b10111101 '
b1100 %
b1100 )
#1900
b10111110 '
b1101 %
b1101 )
#1910
b10111111 '
b1110 %
b1110 )
#1920
b11000000 '
b1111 %
b1111 )
#1930
b1 "
b1 ,
b11000001 '
b1100 &
b1100 *
b0 %
b0 )
#1940
b1001111 "
b1001111 ,
b11000010 '
b1 %
b1 )
#1950
b10010 "
b10010 ,
b11000011 '
b10 %
b10 )
#1960
b110 "
b110 ,
b11000100 '
b11 %
b11 )
#1970
b1001100 "
b1001100 ,
b11000101 '
b100 %
b100 )
#1980
b100100 "
b100100 ,
b11000110 '
b101 %
b101 )
#1990
b100000 "
b100000 ,
b11000111 '
b110 %
b110 )
#2000
b1111 "
b1111 ,
b11001000 '
b111 %
b111 )
#2010
b0 "
b0 ,
b11001001 '
b1000 %
b1000 )
#2020
b1100 "
b1100 ,
b11001010 '
b1001 %
b1001 )
#2030
b1111111 "
b1111111 ,
b11001011 '
b1010 %
b1010 )
#2040
b11001100 '
b1011 %
b1011 )
#2050
b11001101 '
b1100 %
b1100 )
#2060
b11001110 '
b1101 %
b1101 )
#2070
b11001111 '
b1110 %
b1110 )
#2080
b11010000 '
b1111 %
b1111 )
#2090
b1 "
b1 ,
b11010001 '
b1101 &
b1101 *
b0 %
b0 )
#2100
b1001111 "
b1001111 ,
b11010010 '
b1 %
b1 )
#2110
b10010 "
b10010 ,
b11010011 '
b10 %
b10 )
#2120
b110 "
b110 ,
b11010100 '
b11 %
b11 )
#2130
b1001100 "
b1001100 ,
b11010101 '
b100 %
b100 )
#2140
b100100 "
b100100 ,
b11010110 '
b101 %
b101 )
#2150
b100000 "
b100000 ,
b11010111 '
b110 %
b110 )
#2160
b1111 "
b1111 ,
b11011000 '
b111 %
b111 )
#2170
b0 "
b0 ,
b11011001 '
b1000 %
b1000 )
#2180
b1100 "
b1100 ,
b11011010 '
b1001 %
b1001 )
#2190
b1111111 "
b1111111 ,
b11011011 '
b1010 %
b1010 )
#2200
b11011100 '
b1011 %
b1011 )
#2210
b11011101 '
b1100 %
b1100 )
#2220
b11011110 '
b1101 %
b1101 )
#2230
b11011111 '
b1110 %
b1110 )
#2240
b11100000 '
b1111 %
b1111 )
#2250
b1 "
b1 ,
b11100001 '
b1110 &
b1110 *
b0 %
b0 )
#2260
b1001111 "
b1001111 ,
b11100010 '
b1 %
b1 )
#2270
b10010 "
b10010 ,
b11100011 '
b10 %
b10 )
#2280
b110 "
b110 ,
b11100100 '
b11 %
b11 )
#2290
b1001100 "
b1001100 ,
b11100101 '
b100 %
b100 )
#2300
b100100 "
b100100 ,
b11100110 '
b101 %
b101 )
#2310
b100000 "
b100000 ,
b11100111 '
b110 %
b110 )
#2320
b1111 "
b1111 ,
b11101000 '
b111 %
b111 )
#2330
b0 "
b0 ,
b11101001 '
b1000 %
b1000 )
#2340
b1100 "
b1100 ,
b11101010 '
b1001 %
b1001 )
#2350
b1111111 "
b1111111 ,
b11101011 '
b1010 %
b1010 )
#2360
b11101100 '
b1011 %
b1011 )
#2370
b11101101 '
b1100 %
b1100 )
#2380
b11101110 '
b1101 %
b1101 )
#2390
b11101111 '
b1110 %
b1110 )
#2400
b11110000 '
b1111 %
b1111 )
#2410
b1 "
b1 ,
b11110001 '
b1111 &
b1111 *
b0 %
b0 )
#2420
b1001111 "
b1001111 ,
b11110010 '
b1 %
b1 )
#2430
b10010 "
b10010 ,
b11110011 '
b10 %
b10 )
#2440
b110 "
b110 ,
b11110100 '
b11 %
b11 )
#2450
b1001100 "
b1001100 ,
b11110101 '
b100 %
b100 )
#2460
b100100 "
b100100 ,
b11110110 '
b101 %
b101 )
#2470
b100000 "
b100000 ,
b11110111 '
b110 %
b110 )
#2480
b1111 "
b1111 ,
b11111000 '
b111 %
b111 )
#2490
b0 "
b0 ,
b11111001 '
b1000 %
b1000 )
#2500
b1100 "
b1100 ,
b11111010 '
b1001 %
b1001 )
#2510
b1111111 "
b1111111 ,
b11111011 '
b1010 %
b1010 )
#2520
b11111100 '
b1011 %
b1011 )
#2530
b11111101 '
b1100 %
b1100 )
#2540
b11111110 '
b1101 %
b1101 )
#2550
b11111111 '
b1110 %
b1110 )
#2560
b100000000 '
b1111 %
b1111 )
#2570
b1 "
b1 ,
b1 !
b1 -
b1001111 #
b1001111 +
b100000001 '
b1 $
b1 (
b0 &
b0 *
b0 %
b0 )
#2580
b1001111 "
b1001111 ,
b100000010 '
b1 %
b1 )
#2590
b10010 "
b10010 ,
b100000011 '
b10 %
b10 )
#2600
b110 "
b110 ,
b100000100 '
b11 %
b11 )
#2610
b1001100 "
b1001100 ,
b100000101 '
b100 %
b100 )
#2620
b100100 "
b100100 ,
b100000110 '
b101 %
b101 )
#2630
b100000 "
b100000 ,
b100000111 '
b110 %
b110 )
#2640
b1111 "
b1111 ,
b100001000 '
b111 %
b111 )
#2650
b0 "
b0 ,
b100001001 '
b1000 %
b1000 )
#2660
b1100 "
b1100 ,
b100001010 '
b1001 %
b1001 )
#2670
b1111111 "
b1111111 ,
b100001011 '
b1010 %
b1010 )
#2680
b100001100 '
b1011 %
b1011 )
#2690
b100001101 '
b1100 %
b1100 )
#2700
b100001110 '
b1101 %
b1101 )
#2710
b100001111 '
b1110 %
b1110 )
#2720
b100010000 '
b1111 %
b1111 )
#2730
b1 "
b1 ,
b1001111 !
b1001111 -
b100010001 '
b1 &
b1 *
b0 %
b0 )
#2740
b1001111 "
b1001111 ,
b100010010 '
b1 %
b1 )
#2750
b10010 "
b10010 ,
b100010011 '
b10 %
b10 )
#2760
b110 "
b110 ,
b100010100 '
b11 %
b11 )
#2770
b1001100 "
b1001100 ,
b100010101 '
b100 %
b100 )
#2780
b100100 "
b100100 ,
b100010110 '
b101 %
b101 )
#2790
b100000 "
b100000 ,
b100010111 '
b110 %
b110 )
#2800
b1111 "
b1111 ,
b100011000 '
b111 %
b111 )
#2810
b0 "
b0 ,
b100011001 '
b1000 %
b1000 )
#2820
b1100 "
b1100 ,
b100011010 '
b1001 %
b1001 )
#2830
b1111111 "
b1111111 ,
b100011011 '
b1010 %
b1010 )
#2840
b100011100 '
b1011 %
b1011 )
#2850
b100011101 '
b1100 %
b1100 )
#2860
b100011110 '
b1101 %
b1101 )
#2870
b100011111 '
b1110 %
b1110 )
#2880
b100100000 '
b1111 %
b1111 )
#2890
b1 "
b1 ,
b10010 !
b10010 -
b100100001 '
b10 &
b10 *
b0 %
b0 )
#2900
b1001111 "
b1001111 ,
b100100010 '
b1 %
b1 )
#2910
b10010 "
b10010 ,
b100100011 '
b10 %
b10 )
#2920
b110 "
b110 ,
b100100100 '
b11 %
b11 )
#2930
b1001100 "
b1001100 ,
b100100101 '
b100 %
b100 )
#2940
b100100 "
b100100 ,
b100100110 '
b101 %
b101 )
#2950
b100000 "
b100000 ,
b100100111 '
b110 %
b110 )
#2960
b1111 "
b1111 ,
b100101000 '
b111 %
b111 )
#2970
b0 "
b0 ,
b100101001 '
b1000 %
b1000 )
#2980
b1100 "
b1100 ,
b100101010 '
b1001 %
b1001 )
#2990
b1111111 "
b1111111 ,
b100101011 '
b1010 %
b1010 )
#3000
b100101100 '
b1011 %
b1011 )
#3010
b100101101 '
b1100 %
b1100 )
#3020
b100101110 '
b1101 %
b1101 )
#3030
b100101111 '
b1110 %
b1110 )
#3040
b100110000 '
b1111 %
b1111 )
#3050
b1 "
b1 ,
b110 !
b110 -
b100110001 '
b11 &
b11 *
b0 %
b0 )
#3060
b1001111 "
b1001111 ,
b100110010 '
b1 %
b1 )
#3070
b10010 "
b10010 ,
b100110011 '
b10 %
b10 )
#3080
b110 "
b110 ,
b100110100 '
b11 %
b11 )
#3090
b1001100 "
b1001100 ,
b100110101 '
b100 %
b100 )
#3100
b100100 "
b100100 ,
b100110110 '
b101 %
b101 )
#3110
b100000 "
b100000 ,
b100110111 '
b110 %
b110 )
#3120
b1111 "
b1111 ,
b100111000 '
b111 %
b111 )
#3130
b0 "
b0 ,
b100111001 '
b1000 %
b1000 )
#3140
b1100 "
b1100 ,
b100111010 '
b1001 %
b1001 )
#3150
b1111111 "
b1111111 ,
b100111011 '
b1010 %
b1010 )
#3160
b100111100 '
b1011 %
b1011 )
#3170
b100111101 '
b1100 %
b1100 )
#3180
b100111110 '
b1101 %
b1101 )
#3190
b100111111 '
b1110 %
b1110 )
#3200
b101000000 '
b1111 %
b1111 )
#3210
b1 "
b1 ,
b1001100 !
b1001100 -
b101000001 '
b100 &
b100 *
b0 %
b0 )
#3220
b1001111 "
b1001111 ,
b101000010 '
b1 %
b1 )
#3230
b10010 "
b10010 ,
b101000011 '
b10 %
b10 )
#3240
b110 "
b110 ,
b101000100 '
b11 %
b11 )
#3250
b1001100 "
b1001100 ,
b101000101 '
b100 %
b100 )
#3260
b100100 "
b100100 ,
b101000110 '
b101 %
b101 )
#3270
b100000 "
b100000 ,
b101000111 '
b110 %
b110 )
#3280
b1111 "
b1111 ,
b101001000 '
b111 %
b111 )
#3290
b0 "
b0 ,
b101001001 '
b1000 %
b1000 )
#3300
b1100 "
b1100 ,
b101001010 '
b1001 %
b1001 )
#3310
b1111111 "
b1111111 ,
b101001011 '
b1010 %
b1010 )
#3320
b101001100 '
b1011 %
b1011 )
#3330
b101001101 '
b1100 %
b1100 )
#3340
b101001110 '
b1101 %
b1101 )
#3350
b101001111 '
b1110 %
b1110 )
#3360
b101010000 '
b1111 %
b1111 )
#3370
b1 "
b1 ,
b100100 !
b100100 -
b101010001 '
b101 &
b101 *
b0 %
b0 )
#3380
b1001111 "
b1001111 ,
b101010010 '
b1 %
b1 )
#3390
b10010 "
b10010 ,
b101010011 '
b10 %
b10 )
#3400
b110 "
b110 ,
b101010100 '
b11 %
b11 )
#3410
b1001100 "
b1001100 ,
b101010101 '
b100 %
b100 )
#3420
b100100 "
b100100 ,
b101010110 '
b101 %
b101 )
#3430
b100000 "
b100000 ,
b101010111 '
b110 %
b110 )
#3440
b1111 "
b1111 ,
b101011000 '
b111 %
b111 )
#3450
b0 "
b0 ,
b101011001 '
b1000 %
b1000 )
#3460
b1100 "
b1100 ,
b101011010 '
b1001 %
b1001 )
#3470
b1111111 "
b1111111 ,
b101011011 '
b1010 %
b1010 )
#3480
b101011100 '
b1011 %
b1011 )
#3490
b101011101 '
b1100 %
b1100 )
#3500
b101011110 '
b1101 %
b1101 )
#3510
b101011111 '
b1110 %
b1110 )
#3520
b101100000 '
b1111 %
b1111 )
#3530
b1 "
b1 ,
b100000 !
b100000 -
b101100001 '
b110 &
b110 *
b0 %
b0 )
#3540
b1001111 "
b1001111 ,
b101100010 '
b1 %
b1 )
#3550
b10010 "
b10010 ,
b101100011 '
b10 %
b10 )
#3560
b110 "
b110 ,
b101100100 '
b11 %
b11 )
#3570
b1001100 "
b1001100 ,
b101100101 '
b100 %
b100 )
#3580
b100100 "
b100100 ,
b101100110 '
b101 %
b101 )
#3590
b100000 "
b100000 ,
b101100111 '
b110 %
b110 )
#3600
b1111 "
b1111 ,
b101101000 '
b111 %
b111 )
#3610
b0 "
b0 ,
b101101001 '
b1000 %
b1000 )
#3620
b1100 "
b1100 ,
b101101010 '
b1001 %
b1001 )
#3630
b1111111 "
b1111111 ,
b101101011 '
b1010 %
b1010 )
#3640
b101101100 '
b1011 %
b1011 )
#3650
b101101101 '
b1100 %
b1100 )
#3660
b101101110 '
b1101 %
b1101 )
#3670
b101101111 '
b1110 %
b1110 )
#3680
b101110000 '
b1111 %
b1111 )
#3690
b1 "
b1 ,
b1111 !
b1111 -
b101110001 '
b111 &
b111 *
b0 %
b0 )
#3700
b1001111 "
b1001111 ,
b101110010 '
b1 %
b1 )
#3710
b10010 "
b10010 ,
b101110011 '
b10 %
b10 )
#3720
b110 "
b110 ,
b101110100 '
b11 %
b11 )
#3730
b1001100 "
b1001100 ,
b101110101 '
b100 %
b100 )
#3740
b100100 "
b100100 ,
b101110110 '
b101 %
b101 )
#3750
b100000 "
b100000 ,
b101110111 '
b110 %
b110 )
#3760
b1111 "
b1111 ,
b101111000 '
b111 %
b111 )
#3770
b0 "
b0 ,
b101111001 '
b1000 %
b1000 )
#3780
b1100 "
b1100 ,
b101111010 '
b1001 %
b1001 )
#3790
b1111111 "
b1111111 ,
b101111011 '
b1010 %
b1010 )
#3800
b101111100 '
b1011 %
b1011 )
#3810
b101111101 '
b1100 %
b1100 )
#3820
b101111110 '
b1101 %
b1101 )
#3830
b101111111 '
b1110 %
b1110 )
#3840
b110000000 '
b1111 %
b1111 )
#3850
b1 "
b1 ,
b0 !
b0 -
b110000001 '
b1000 &
b1000 *
b0 %
b0 )
#3860
b1001111 "
b1001111 ,
b110000010 '
b1 %
b1 )
#3870
b10010 "
b10010 ,
b110000011 '
b10 %
b10 )
#3880
b110 "
b110 ,
b110000100 '
b11 %
b11 )
#3890
b1001100 "
b1001100 ,
b110000101 '
b100 %
b100 )
#3900
b100100 "
b100100 ,
b110000110 '
b101 %
b101 )
#3910
b100000 "
b100000 ,
b110000111 '
b110 %
b110 )
#3920
b1111 "
b1111 ,
b110001000 '
b111 %
b111 )
#3930
b0 "
b0 ,
b110001001 '
b1000 %
b1000 )
#3940
b1100 "
b1100 ,
b110001010 '
b1001 %
b1001 )
#3950
b1111111 "
b1111111 ,
b110001011 '
b1010 %
b1010 )
#3960
b110001100 '
b1011 %
b1011 )
#3970
b110001101 '
b1100 %
b1100 )
#3980
b110001110 '
b1101 %
b1101 )
#3990
b110001111 '
b1110 %
b1110 )
#4000
b110010000 '
b1111 %
b1111 )
#4010
b1 "
b1 ,
b1100 !
b1100 -
b110010001 '
b1001 &
b1001 *
b0 %
b0 )
#4020
b1001111 "
b1001111 ,
b110010010 '
b1 %
b1 )
#4030
b10010 "
b10010 ,
b110010011 '
b10 %
b10 )
#4040
b110 "
b110 ,
b110010100 '
b11 %
b11 )
#4050
b1001100 "
b1001100 ,
b110010101 '
b100 %
b100 )
#4060
b100100 "
b100100 ,
b110010110 '
b101 %
b101 )
#4070
b100000 "
b100000 ,
b110010111 '
b110 %
b110 )
#4080
b1111 "
b1111 ,
b110011000 '
b111 %
b111 )
#4090
b0 "
b0 ,
b110011001 '
b1000 %
b1000 )
#4100
b1100 "
b1100 ,
b110011010 '
b1001 %
b1001 )
#4110
b1111111 "
b1111111 ,
b110011011 '
b1010 %
b1010 )
#4120
b110011100 '
b1011 %
b1011 )
